{
    "00016179_R": {},
    "00285176_L": {
        "20190116": {
            "center": [
                141,
                162
            ],
            "matching": [
                102.04284304047384,
                28.042978107773834,
                5.485183615661502
            ],
            "original": [
                100.71898650871998,
                28.09969013862275,
                3.346239575126068
            ],
            "radius": 100,
            "rotation_angle": -5.931204429984224,
            "rotation_rad": -0.1035190459120982,
            "scale": 0.8064024728673646,
            "translation": [
                14.14154483231431,
                5.516605497027896
            ]
        },
        "20190522": {
            "center": [
                147,
                170
            ],
            "matching": [
                101.81656055563595,
                28.05261938731682,
                5.086334973026526
            ],
            "original": [
                103.42786861525104,
                27.984427857939806,
                5.631237492764531
            ],
            "radius": 113,
            "rotation_angle": 7.16874849041862,
            "rotation_rad": 0.1251182644051781,
            "scale": 1.1686265662044335,
            "translation": [
                -3.193249105971997,
                -4.221256339958266
            ]
        }
    },
    "00468301_L": {},
    "00563175_L": {
        "20160711": {
            "center": [
                145,
                151
            ],
            "matching": [
                96.95484140600941,
                28.26510860569045,
                26.546655781791944
            ],
            "original": [
                102.12288284721306,
                28.039572947771674,
                3.094428447556334
            ],
            "radius": 84,
            "rotation_angle": -0.5232693316179203,
            "rotation_rad": -0.009132772711442777,
            "scale": 1.0149784063490583,
            "translation": [
                -3.6782909901872145,
                0.5797919050596079
            ]
        },
        "20160808": {
            "center": [
                141,
                146
            ],
            "radius": 75,
            "rotation_angle": -1.4943253437383395,
            "rotation_rad": -0.026080897344230053,
            "scale": 0.9714018760107034,
            "translation": [
                -3.088074642848156,
                5.112669784946036
            ]
        },
        "20161107": {
            "center": [
                172,
                167
            ],
            "radius": 75,
            "rotation_angle": 1.1610769854297625,
            "rotation_rad": 0.020264616264879583,
            "scale": 1.075692416928193,
            "translation": [
                -39.4074064376949,
                -17.820561189727883
            ]
        }
    },
    "00871678_L": {
        "20170313": {
            "center": [
                154,
                165
            ],
            "radius": 99,
            "rotation_angle": -2.4867161312297243,
            "rotation_rad": -0.043401384052414074,
            "scale": 0.9826949365252438,
            "translation": [
                -3.8061795004669747,
                8.399710600483544
            ]
        },
        "20170828": {
            "center": [
                142,
                147
            ],
            "radius": 83,
            "rotation_angle": 0,
            "rotation_rad": 0,
            "scale": 1,
            "translation": [
                0,
                0
            ]
        },
        "20171030": {
            "center": [
                141,
                150
            ],
            "matching": [
                100.72744575127643,
                28.099325396261786,
                6.829179724203326
            ],
            "original": [
                101.18810402990518,
                28.079509022953854,
                5.435623101141019
            ],
            "radius": 87,
            "rotation_angle": -2.149495437358067,
            "rotation_rad": -0.037515772638493795,
            "scale": 1.048262407410605,
            "translation": [
                -4.622384656795369,
                1.5548612589697797
            ]
        },
        "20180205": {
            "center": [
                141,
                149
            ],
            "radius": 88,
            "rotation_angle": 0,
            "rotation_rad": 0,
            "scale": 1,
            "translation": [
                0,
                0
            ]
        },
        "20180917": {
            "center": [
                154,
                140
            ],
            "radius": 98,
            "rotation_angle": 4.7336470734412845,
            "rotation_rad": 0.08261772705894424,
            "scale": 1.1169341590095139,
            "translation": [
                8.868728953910278,
                3.745709576064087
            ]
        },
        "20190327": {
            "center": [
                142,
                150
            ],
            "radius": 77,
            "rotation_angle": -51.24182634220796,
            "rotation_rad": -0.8943385844066915,
            "scale": 1.8028448916092215,
            "translation": [
                -118.91743399761805,
                148.9866180026771
            ]
        }
    },
    "01790839_R": {
        "20211102": {
            "center": [
                145,
                133
            ],
            "matching": [
                100.09854263918935,
                28.12652606349287,
                4.2330048977077395
            ],
            "original": [
                99.14873429731679,
                28.167931863628937,
                4.373892034215662
            ],
            "radius": 79,
            "rotation_angle": 28.070140067865157,
            "rotation_rad": 0.48991636568023156,
            "scale": 1.5173104655076126,
            "translation": [
                -2.0786976285487313,
                -110.63815858895143
            ]
        }
    },
    "01836108_L": {
        "20160921": {
            "center": [
                157,
                150
            ],
            "radius": 75,
            "rotation_angle": 0,
            "rotation_rad": 0,
            "scale": 1,
            "translation": [
                0,
                0
            ]
        },
        "20161205": {
            "center": [
                154,
                152
            ],
            "radius": 73,
            "rotation_angle": 0,
            "rotation_rad": 0,
            "scale": 1,
            "translation": [
                0,
                0
            ]
        },
        "20170220": {
            "center": [
                155,
                145
            ],
            "radius": 79,
            "rotation_angle": 0,
            "rotation_rad": 0,
            "scale": 1,
            "translation": [
                0,
                0
            ]
        },
        "20170424": {
            "center": [
                149,
                146
            ],
            "radius": 81,
            "rotation_angle": 0,
            "rotation_rad": 0,
            "scale": 1,
            "translation": [
                0,
                0
            ]
        }
    },
    "02875773_L": {
        "20220420": {
            "center": [
                145,
                145
            ],
            "matching": [
                98.38455888999367,
                28.201534180776594,
                19.580350895616217
            ],
            "original": [
                103.39621937991504,
                27.98575701534148,
                4.104994575193417
            ],
            "radius": 90,
            "rotation_angle": 0.09929923518757139,
            "rotation_rad": 0.0017330985987353297,
            "scale": 1.0270083688232678,
            "translation": [
                -1.1128398251229115,
                -7.65610593039618
            ]
        }
    },
    "03254241_L": {
        "20161017": {
            "center": [
                132,
                175
            ],
            "radius": 94,
            "rotation_angle": 0,
            "rotation_rad": 0,
            "scale": 1,
            "translation": [
                0,
                0
            ]
        },
        "20161128": {
            "center": [
                133,
                152
            ],
            "radius": 100,
            "rotation_angle": 0,
            "rotation_rad": 0,
            "scale": 1,
            "translation": [
                0,
                0
            ]
        },
        "20161226": {
            "center": [
                150,
                161
            ],
            "radius": 95,
            "rotation_angle": 0,
            "rotation_rad": 0,
            "scale": 1,
            "translation": [
                0,
                0
            ]
        },
        "20170320": {
            "center": [
                84,
                158
            ],
            "radius": 84,
            "rotation_angle": 0,
            "rotation_rad": 0,
            "scale": 1,
            "translation": [
                0,
                0
            ]
        },
        "20170807": {
            "center": [
                166,
                167
            ],
            "radius": 107,
            "rotation_angle": 0,
            "rotation_rad": 0,
            "scale": 1,
            "translation": [
                0,
                0
            ]
        },
        "20171013": {
            "center": [
                167,
                166
            ],
            "radius": 99,
            "rotation_angle": 0,
            "rotation_rad": 0,
            "scale": 1,
            "translation": [
                0,
                0
            ]
        },
        "20171115": {
            "center": [
                165,
                163
            ],
            "radius": 103,
            "rotation_angle": 0,
            "rotation_rad": 0,
            "scale": 1,
            "translation": [
                0,
                0
            ]
        },
        "20180110": {
            "center": [
                158,
                162
            ],
            "radius": 101,
            "rotation_angle": 0,
            "rotation_rad": 0,
            "scale": 1,
            "translation": [
                0,
                0
            ]
        },
        "20180207": {
            "center": [
                158,
                163
            ],
            "radius": 98,
            "rotation_angle": 0,
            "rotation_rad": 0,
            "scale": 1,
            "translation": [
                0,
                0
            ]
        },
        "20180314": {
            "center": [
                164,
                165
            ],
            "radius": 98,
            "rotation_angle": 0,
            "rotation_rad": 0,
            "scale": 1,
            "translation": [
                0,
                0
            ]
        },
        "20180523": {
            "center": [
                165,
                163
            ],
            "radius": 104,
            "rotation_angle": 0,
            "rotation_rad": 0,
            "scale": 1,
            "translation": [
                0,
                0
            ]
        },
        "20180627": {
            "center": [
                162,
                162
            ],
            "radius": 103,
            "rotation_angle": 0,
            "rotation_rad": 0,
            "scale": 1,
            "translation": [
                0,
                0
            ]
        },
        "20181003": {
            "center": [
                164,
                158
            ],
            "radius": 100,
            "rotation_angle": 0,
            "rotation_rad": 0,
            "scale": 1,
            "translation": [
                0,
                0
            ]
        },
        "20190306": {
            "center": [
                167,
                157
            ],
            "radius": 105,
            "rotation_angle": 0,
            "rotation_rad": 0,
            "scale": 1,
            "translation": [
                0,
                0
            ]
        },
        "20190605": {
            "center": [
                133,
                158
            ],
            "radius": 105,
            "rotation_angle": 0,
            "rotation_rad": 0,
            "scale": 1,
            "translation": [
                0,
                0
            ]
        }
    },
    "03408585_R": {},
    "03860215_L": {},
    "03978730_R": {
        "20211124": {
            "center": [
                152,
                144
            ],
            "matching": [
                96.12315611983965,
                28.3025233882211,
                19.476981179697507
            ],
            "original": [
                96.58803166839749,
                28.281570450361713,
                0.7870209331059091
            ],
            "radius": 95,
            "rotation_angle": 0.9140270093294032,
            "rotation_rad": 0.015952780764955012,
            "scale": 1.0145549839403432,
            "translation": [
                1.8116826166120887,
                -1.1117278564794972
            ]
        }
    },
    "04851616_R": {},
    "04978848_R": {
        "20170111": {
            "center": [
                174,
                148
            ],
            "radius": 82,
            "rotation_angle": 0,
            "rotation_rad": 0,
            "scale": 1,
            "translation": [
                0,
                0
            ]
        },
        "20180801": {
            "center": [
                149,
                144
            ],
            "radius": 84,
            "rotation_angle": -4.568260609086939,
            "rotation_rad": -0.07973118871772866,
            "scale": 0.9379512976356009,
            "translation": [
                2.636142795187581,
                5.920702310018882
            ]
        },
        "20200617": {
            "center": [
                157,
                134
            ],
            "matching": [
                100.26591318170131,
                28.11927047320816,
                5.894857173780559
            ],
            "original": [
                101.76394960143996,
                28.05486406659245,
                4.983494428089653
            ],
            "radius": 83,
            "rotation_angle": 5.70582007660983,
            "rotation_rad": 0.09958534686323663,
            "scale": 1.5256292224144365,
            "translation": [
                -26.171488632956468,
                6.314126915788194
            ]
        }
    },
    "05084585_L": {
        "20210930": {
            "center": [
                124,
                134
            ],
            "matching": [
                98.51279237655213,
                28.195877314076952,
                6.731667347698986
            ],
            "original": [
                97.54248917123881,
                28.238865267792683,
                5.358157460845264
            ],
            "radius": 82,
            "rotation_angle": -2.4684098750264405,
            "rotation_rad": -0.043081879607953136,
            "scale": 0.8511882047701528,
            "translation": [
                23.21119323211076,
                19.34450405983317
            ]
        }
    },
    "05655586_L": {},
    "05655586_R": {},
    "06271674_L": {},
    "07838199_L": {
        "20220328": {
            "center": [
                142,
                171
            ],
            "matching": [
                99.62996110719403,
                28.14690400086491,
                5.252937754424857
            ],
            "original": [
                99.3538563013169,
                28.158956324731083,
                4.758132916715619
            ],
            "radius": 84,
            "rotation_angle": 2.540616778193886,
            "rotation_rad": 0.04434212781089379,
            "scale": 1.055472063133863,
            "translation": [
                -8.18244397750751,
                -4.501574387379989
            ]
        }
    },
    "08476328_L": {},
    "08532554_R": {
        "20171206": {
            "center": [
                146,
                147
            ],
            "radius": 96,
            "rotation_angle": -3.668540797477569,
            "rotation_rad": -0.06402811565972207,
            "scale": 0.8735800736090877,
            "translation": [
                11.872692853794106,
                8.573201507053312
            ]
        },
        "20180103": {
            "center": [
                142,
                145
            ],
            "radius": 100,
            "rotation_angle": 0,
            "rotation_rad": 0,
            "scale": 1,
            "translation": [
                0,
                0
            ]
        },
        "20190401": {
            "center": [
                139,
                165
            ],
            "radius": 98,
            "rotation_angle": -1.1200897006689925,
            "rotation_rad": -0.019549253194351652,
            "scale": 0.9630555780896051,
            "translation": [
                14.737903875197517,
                -18.598796727475985
            ]
        },
        "20190717": {
            "center": [
                139,
                165
            ],
            "matching": [
                97.89802631578948,
                28.223064246194408,
                8.973704081453114
            ],
            "original": [
                99.6353154227031,
                28.14667060850263,
                4.682709861719292
            ],
            "radius": 97,
            "rotation_angle": -0.21104086741823389,
            "rotation_rad": -0.0036833579927130064,
            "scale": 1.0493929698804434,
            "translation": [
                4.217491361357865,
                -21.181591275031927
            ]
        },
        "20200814": {
            "center": [
                134,
                157
            ],
            "radius": 90,
            "rotation_angle": -2.508316802111273,
            "rotation_rad": -0.04377838687993677,
            "scale": 0.9886626080903615,
            "translation": [
                17.912837171476134,
                -7.985749823344399
            ]
        }
    },
    "08663464_R": {},
    "08707452_L": {
        "20170118": {
            "center": [
                156,
                153
            ],
            "radius": 94,
            "rotation_angle": 1.1432840476850648,
            "rotation_rad": 0.019954070917632235,
            "scale": 0.971925691112489,
            "translation": [
                46.50879745357918,
                11.780436243102102
            ]
        },
        "20170222": {
            "center": [
                159,
                153
            ],
            "matching": [
                96.61121659498069,
                28.28052809788703,
                27.17452698000851
            ],
            "original": [
                102.19319047803567,
                28.036584028024908,
                3.5080477198442246
            ],
            "radius": 99,
            "rotation_angle": -0.37651954451500647,
            "rotation_rad": -0.006571505749896219,
            "scale": 0.9695586166894915,
            "translation": [
                40.23251954537871,
                13.573929306080927
            ]
        },
        "20170329": {
            "center": [
                160,
                153
            ],
            "radius": 88,
            "rotation_angle": -2.438326247561072,
            "rotation_rad": -0.04255682125773906,
            "scale": 0.9688008312368657,
            "translation": [
                39.64370294982257,
                18.982674439340414
            ]
        },
        "20170503": {
            "center": [
                166,
                151
            ],
            "radius": 88,
            "rotation_angle": -1.6681028745539974,
            "rotation_rad": -0.02911388742294919,
            "scale": 0.9938885808303264,
            "translation": [
                29.497165076635298,
                17.004100011093897
            ]
        },
        "20170531": {
            "center": [
                157,
                136
            ],
            "radius": 88,
            "rotation_angle": -1.1567175640160945,
            "rotation_rad": -0.020188530007729133,
            "scale": 0.9756102929421485,
            "translation": [
                45.753302166763305,
                34.436631000573655
            ]
        },
        "20170705": {
            "center": [
                157,
                131
            ],
            "matching": [
                100.39071648799253,
                28.11386807067363,
                8.026826040751176
            ],
            "original": [
                101.50151330863011,
                28.066078435774166,
                3.8506856286968163
            ],
            "radius": 88,
            "rotation_angle": 0.850898278649818,
            "rotation_rad": 0.014850976561991495,
            "scale": 0.972023020048141,
            "translation": [
                44.57617991970017,
                33.45095703707135
            ]
        },
        "20170802": {
            "center": [
                153,
                136
            ],
            "matching": [
                97.85911493477283,
                28.22479077307086,
                15.860018691796979
            ],
            "original": [
                100.07063933873144,
                28.127736864213993,
                4.736892654275597
            ],
            "radius": 94,
            "rotation_angle": -0.2337250491234335,
            "rotation_rad": -0.004079271651589401,
            "scale": 0.9758248204968367,
            "translation": [
                45.3555202663416,
                29.019976787415104
            ]
        }
    },
    "09065071_R": {},
    "09227477_L": {
        "20170116": {
            "center": [
                147,
                175
            ],
            "matching": [
                99.93183769243977,
                28.133764869430347,
                4.7291201176255395
            ],
            "original": [
                101.84458307102386,
                28.05142426254612,
                3.171970347738001
            ],
            "radius": 83,
            "rotation_angle": -0.5150623326996105,
            "rotation_rad": -0.008989533558610657,
            "scale": 0.9738605479059536,
            "translation": [
                -8.380160575986359,
                8.132971123139939
            ]
        },
        "20171011": {
            "center": [
                140,
                153
            ],
            "matching": [
                99.14726849494436,
                28.167996069651544,
                17.706043976204352
            ],
            "original": [
                102.97735263451419,
                28.003386381756922,
                4.054098698565648
            ],
            "radius": 87,
            "rotation_angle": -1.1161486473752742,
            "rotation_rad": -0.0194804688383797,
            "scale": 1.0060182500606567,
            "translation": [
                -2.9326615771265807,
                31.816634525537566
            ]
        },
        "20180207": {
            "center": [
                138,
                150
            ],
            "radius": 84,
            "rotation_angle": -1.4914337310179588,
            "rotation_rad": -0.026030429181566863,
            "scale": 0.9463805861981582,
            "translation": [
                0.7730131522879873,
                35.15570735676671
            ]
        },
        "20180912": {
            "center": [
                139,
                154
            ],
            "radius": 83,
            "rotation_angle": 0,
            "rotation_rad": 0,
            "scale": 1,
            "translation": [
                0,
                0
            ]
        },
        "20190724": {
            "center": [
                133,
                146
            ],
            "radius": 86,
            "rotation_angle": 0,
            "rotation_rad": 0,
            "scale": 1,
            "translation": [
                0,
                0
            ]
        }
    },
    "09958282_L": {
        "20161205": {
            "center": [
                146,
                149
            ],
            "matching": [
                102.70078483809081,
                28.015065983850466,
                4.062160245404279
            ],
            "original": [
                101.6545665949654,
                28.05953467786155,
                4.591723530371091
            ],
            "radius": 76,
            "rotation_angle": 5.3592763787208995,
            "rotation_rad": 0.09353701833303826,
            "scale": 1.0876202391814898,
            "translation": [
                7.391580823909365,
                0.5690912692287782
            ]
        },
        "20170109": {
            "center": [
                142,
                147
            ],
            "radius": 75,
            "rotation_angle": 3.039763320010111,
            "rotation_rad": 0.05305387841553047,
            "scale": 1.0845477096671894,
            "translation": [
                8.348639008188528,
                1.639891673023385
            ]
        },
        "20170220": {
            "center": [
                148,
                147
            ],
            "radius": 77,
            "rotation_angle": -1.2814339540786626,
            "rotation_rad": -0.02236524164552248,
            "scale": 0.9726480668288872,
            "translation": [
                2.9133720945592927,
                5.369154539168761
            ]
        },
        "20170320": {
            "center": [
                149,
                149
            ],
            "radius": 78,
            "rotation_angle": -2.4275225149422597,
            "rotation_rad": -0.04236826055203568,
            "scale": 0.9986412474877678,
            "translation": [
                -1.6158379373382132,
                5.931744458169021
            ]
        },
        "20170417": {
            "center": [
                153,
                182
            ],
            "matching": [
                103.44569046567212,
                27.98367958142262,
                3.7627855245371893
            ],
            "original": [
                103.63883508342678,
                27.97557838063993,
                2.499666552946533
            ],
            "radius": 74,
            "rotation_angle": -0.4861725218064003,
            "rotation_rad": -0.008485311238245615,
            "scale": 0.9589105669760121,
            "translation": [
                -1.7623454312913793,
                -32.74599076793206
            ]
        },
        "20170612": {
            "center": [
                143,
                194
            ],
            "matching": [
                103.04873544861317,
                28.000376941176377,
                0.18446094237450159
            ],
            "original": [
                101.98316842801353,
                28.045518603022824,
                2.632225627163437
            ],
            "radius": 83,
            "rotation_angle": 0.8804915044473763,
            "rotation_rad": 0.015367475788445013,
            "scale": 1.005253204509874,
            "translation": [
                6.700664969489097,
                -42.08337039663688
            ]
        },
        "20170807": {
            "center": [
                143,
                199
            ],
            "radius": 78,
            "rotation_angle": 1.5147103307111522,
            "rotation_rad": 0.026436682484881787,
            "scale": 1.0518064080433123,
            "translation": [
                5.541624812413318,
                -49.43308965047346
            ]
        },
        "20171016": {
            "center": [
                144,
                200
            ],
            "radius": 86,
            "rotation_angle": -1.654720986382923,
            "rotation_rad": -0.028880329414230264,
            "scale": 1.0001474339012892,
            "translation": [
                4.178436859778635,
                -50.06486279464344
            ]
        },
        "20171211": {
            "center": [
                142,
                144
            ],
            "matching": [
                102.67572488282548,
                28.016125832453138,
                3.571821765420221
            ],
            "original": [
                101.24667544194172,
                28.07699589336012,
                3.657172258101716
            ],
            "radius": 79,
            "rotation_angle": -0.22099062338956602,
            "rotation_rad": -0.003857013994182718,
            "scale": 0.8814630393719222,
            "translation": [
                9.731404948511894,
                1.4374193873122323
            ]
        },
        "20180129": {
            "center": [
                136,
                146
            ],
            "matching": [
                101.4023950037243,
                28.070321482313613,
                10.596139710644172
            ],
            "original": [
                101.39485475276457,
                28.070644434364436,
                2.864899206180856
            ],
            "radius": 82,
            "rotation_angle": -1.501208182292589,
            "rotation_rad": -0.02620102553888491,
            "scale": 0.971549178878384,
            "translation": [
                19.469683349401848,
                1.9227980577043837
            ]
        },
        "20180326": {
            "center": [
                136,
                142
            ],
            "radius": 76,
            "rotation_angle": 3.0313610407100735,
            "rotation_rad": 0.05290723097707265,
            "scale": 1.0514335374935802,
            "translation": [
                14.297607423602159,
                5.566749869423731
            ]
        },
        "20180521": {
            "center": [
                132,
                145
            ],
            "matching": [
                102.85943902410388,
                28.008362094362177,
                5.687001919616939
            ],
            "original": [
                105.12411210125275,
                27.91378020182321,
                2.376955590006061
            ],
            "radius": 78,
            "rotation_angle": 1.2969078874646471,
            "rotation_rad": 0.022635312731342186,
            "scale": 1.0190988469143376,
            "translation": [
                17.235282766812432,
                3.4779941533093393
            ]
        },
        "20180716": {
            "center": [
                135,
                145
            ],
            "matching": [
                102.25454312473789,
                28.03397748245522,
                6.3450716915811
            ],
            "original": [
                105.21026513210009,
                27.910222458340588,
                3.3939226545226813
            ],
            "radius": 84,
            "rotation_angle": 1.2447315672565222,
            "rotation_rad": 0.021724664152135555,
            "scale": 0.9977465708665363,
            "translation": [
                14.30347294026761,
                5.213148594915808
            ]
        },
        "20180910": {
            "center": [
                134,
                144
            ],
            "matching": [
                103.11289329809189,
                27.99767387746192,
                3.057063462095204
            ],
            "original": [
                104.96180165827872,
                27.920490841532715,
                2.5724918291371077
            ],
            "radius": 74,
            "rotation_angle": 4.001672252367629,
            "rotation_rad": 0.06984235638951258,
            "scale": 1.073036706617754,
            "translation": [
                13.549623696625417,
                4.998529868749003
            ]
        },
        "20181212": {
            "center": [
                126,
                148
            ],
            "matching": [
                102.78482000549602,
                28.011513811760132,
                3.4363640603231147
            ],
            "original": [
                102.78482000549602,
                28.011513811760132,
                3.4363640603231147
            ],
            "radius": 78,
            "rotation_angle": 0,
            "rotation_rad": 0,
            "scale": 1,
            "translation": [
                0,
                0
            ]
        },
        "20190306": {
            "center": [
                127,
                148
            ],
            "matching": [
                100.71900951406174,
                28.099689146645748,
                28.50314782192665
            ],
            "original": [
                104.84133150340784,
                27.92547832941777,
                2.57375285210449
            ],
            "radius": 78,
            "rotation_angle": -0.8586892910746468,
            "rotation_rad": -0.014986955380868543,
            "scale": 0.9965040132911671,
            "translation": [
                22.387503137316074,
                4.030521096532041
            ]
        },
        "20190529": {
            "center": [
                128,
                147
            ],
            "matching": [
                102.59589122432016,
                28.019503924345692,
                7.604966460093711
            ],
            "original": [
                101.89444246526541,
                28.04929863539488,
                2.8633308533864184
            ],
            "radius": 77,
            "rotation_angle": -2.2604009187182292,
            "rotation_rad": -0.039451438446737826,
            "scale": 1.0087745232177534,
            "translation": [
                19.731539455365365,
                2.9197494915557627
            ]
        },
        "20191106": {
            "center": [
                126,
                138
            ],
            "matching": [
                102.4161242104248,
                28.02712024302895,
                2.2271311038537562
            ],
            "original": [
                104.76589999517817,
                27.928604127031317,
                2.8279422945418915
            ],
            "radius": 77,
            "rotation_angle": 1.6707951213253582,
            "rotation_rad": 0.029160875993385627,
            "scale": 0.9890460819687504,
            "translation": [
                23.614125123395212,
                13.074592445485052
            ]
        },
        "20200422": {
            "center": [
                129,
                146
            ],
            "matching": [
                101.29808829792267,
                28.074791114552838,
                17.433538834695327
            ],
            "original": [
                104.59750153787914,
                27.935590499625768,
                2.62009512159911
            ],
            "radius": 80,
            "rotation_angle": -1.6355859735031402,
            "rotation_rad": -0.02854636043706653,
            "scale": 0.9822035703385248,
            "translation": [
                20.221384145002645,
                7.901670590997583
            ]
        },
        "20200923": {
            "center": [
                128,
                137
            ],
            "matching": [
                104.47418300293887,
                27.940713772590207,
                2.8380759652462584
            ],
            "original": [
                104.47418300293887,
                27.940713772590207,
                2.8380759652462584
            ],
            "radius": 77,
            "rotation_angle": 0,
            "rotation_rad": 0,
            "scale": 1,
            "translation": [
                0,
                0
            ]
        },
        "20210310": {
            "center": [
                152,
                141
            ],
            "matching": [
                102.56383854518646,
                28.020860945219805,
                7.531152859150682
            ],
            "original": [
                104.99856238864656,
                27.91897007997516,
                2.491743032278165
            ],
            "radius": 77,
            "rotation_angle": 4.942790514297013,
            "rotation_rad": 0.08626796871082675,
            "scale": 1.066276128651595,
            "translation": [
                -2.1101058942761455,
                8.596110359839926
            ]
        }
    },
    "10006476_R": {},
    "10045360_R": {},
    "10284504_L": {
        "20160504": {
            "center": [
                139,
                141
            ],
            "matching": [
                97.1787237126602,
                28.25509169867912,
                38.66129151441246
            ],
            "original": [
                101.69666735115416,
                28.057736397516436,
                2.318015683058896
            ],
            "radius": 93,
            "rotation_angle": 0.11422824607652211,
            "rotation_rad": 0.0019936589928136053,
            "scale": 1.0067222130285722,
            "translation": [
                23.31331743989513,
                10.787395994077428
            ]
        },
        "20160601": {
            "center": [
                150,
                153
            ],
            "radius": 91,
            "rotation_angle": -1.4116481449632037,
            "rotation_rad": -0.024637908009278113,
            "scale": 0.9710192423748292,
            "translation": [
                13.98989522841913,
                0.28225650093893506
            ]
        },
        "20160622": {
            "center": [
                152,
                141
            ],
            "matching": [
                99.06731998295696,
                28.17149946460769,
                14.200699243739622
            ],
            "original": [
                104.61821237513611,
                27.93473065958819,
                3.5742821421072075
            ],
            "radius": 99,
            "rotation_angle": -0.7766420818836891,
            "rotation_rad": -0.01355496143841378,
            "scale": 1.001777678196552,
            "translation": [
                14.013884738574049,
                13.400191549107717
            ]
        },
        "20160715": {
            "center": [
                145,
                153
            ],
            "matching": [
                98.60450369136059,
                28.191836093786506,
                27.177287182570343
            ],
            "original": [
                100.58988868059895,
                28.105260333380613,
                3.500006285006252
            ],
            "radius": 96,
            "rotation_angle": -0.07055761937011575,
            "rotation_rad": -0.0012314627703774474,
            "scale": 1.0131178379997559,
            "translation": [
                20.22877096429808,
                -1.5091460290190355
            ]
        },
        "20160817": {
            "center": [
                157,
                147
            ],
            "matching": [
                97.97651727941594,
                28.219583631145497,
                13.90549774977225
            ],
            "original": [
                100.5789599372278,
                28.105732204942985,
                5.029680185709841
            ],
            "radius": 88,
            "rotation_angle": 0.9857064074494195,
            "rotation_rad": 0.017203822267997132,
            "scale": 1.020135032093307,
            "translation": [
                7.400252657550652,
                10.110678184657303
            ]
        },
        "20160919": {
            "center": [
                158,
                137
            ],
            "radius": 92,
            "rotation_angle": -1.8689333086770248,
            "rotation_rad": -0.03261903973660559,
            "scale": 0.9713688277920439,
            "translation": [
                5.321588419470373,
                16.71717714597795
            ]
        },
        "20161017": {
            "center": [
                164,
                147
            ],
            "matching": [
                99.4954170281875,
                28.1527728419463,
                19.372603341469674
            ],
            "original": [
                101.07022403168035,
                28.084571325113966,
                2.9026903231319094
            ],
            "radius": 90,
            "rotation_angle": 0.3990413121850215,
            "rotation_rad": 0.006964584749107192,
            "scale": 0.9903624614590667,
            "translation": [
                6.320210263316312,
                6.128209439850117
            ]
        },
        "20161114": {
            "center": [
                140,
                162
            ],
            "matching": [
                97.25736085176895,
                28.25157880368063,
                24.342714549495035
            ],
            "original": [
                99.82570146042266,
                28.13837990267796,
                3.4044156244650647
            ],
            "radius": 103,
            "rotation_angle": -0.641979574337221,
            "rotation_rad": -0.011204657302736199,
            "scale": 1.0203203511966772,
            "translation": [
                27.6983202532153,
                -7.651611516367225
            ]
        },
        "20170301": {
            "center": [
                180,
                164
            ],
            "radius": 88,
            "rotation_angle": 0,
            "rotation_rad": 0,
            "scale": 1,
            "translation": [
                0,
                0
            ]
        },
        "20170405": {
            "center": [
                164,
                165
            ],
            "radius": 91,
            "rotation_angle": 0,
            "rotation_rad": 0,
            "scale": 1,
            "translation": [
                0,
                0
            ]
        },
        "20170515": {
            "center": [
                162,
                161
            ],
            "matching": [
                98.21640825432236,
                28.208963128056787,
                4.399463949974049
            ],
            "original": [
                98.21640825432236,
                28.208963128056787,
                4.399463949974049
            ],
            "radius": 86,
            "rotation_angle": 0,
            "rotation_rad": 0,
            "scale": 1,
            "translation": [
                0,
                0
            ]
        },
        "20170612": {
            "center": [
                164,
                165
            ],
            "matching": [
                96.7908200020583,
                28.27246191694914,
                17.178403693477076
            ],
            "original": [
                99.4205440761112,
                28.156042253941767,
                6.135651527241515
            ],
            "radius": 85,
            "rotation_angle": -0.2430925858946281,
            "rotation_rad": -0.0042427660110483855,
            "scale": 0.9759231240255338,
            "translation": [
                -0.18025973821370656,
                -8.640110700657758
            ]
        },
        "20170710": {
            "center": [
                158,
                164
            ],
            "radius": 90,
            "rotation_angle": 4.714598997810934,
            "rotation_rad": 0.08228527542302573,
            "scale": 1.1577780952496353,
            "translation": [
                -5.609676051001806,
                -16.046530377871825
            ]
        },
        "20170807": {
            "center": [
                164,
                169
            ],
            "radius": 95,
            "rotation_angle": 0,
            "rotation_rad": 0,
            "scale": 1,
            "translation": [
                0,
                0
            ]
        },
        "20171016": {
            "center": [
                159,
                168
            ],
            "radius": 88,
            "rotation_angle": 0,
            "rotation_rad": 0,
            "scale": 1,
            "translation": [
                0,
                0
            ]
        },
        "20171120": {
            "center": [
                174,
                191
            ],
            "radius": 113,
            "rotation_angle": 0,
            "rotation_rad": 0,
            "scale": 1,
            "translation": [
                0,
                0
            ]
        },
        "20180108": {
            "center": [
                150,
                154
            ],
            "matching": [
                105.25387605710648,
                27.908422628284498,
                6.058235896204819
            ],
            "original": [
                105.25387605710648,
                27.908422628284498,
                6.058235896204819
            ],
            "radius": 126,
            "rotation_angle": 0,
            "rotation_rad": 0,
            "scale": 1,
            "translation": [
                0,
                0
            ]
        },
        "20180305": {
            "center": [
                164,
                162
            ],
            "radius": 92,
            "rotation_angle": 0,
            "rotation_rad": 0,
            "scale": 1,
            "translation": [
                0,
                0
            ]
        },
        "20180514": {
            "center": [
                167,
                171
            ],
            "radius": 92,
            "rotation_angle": 0,
            "rotation_rad": 0,
            "scale": 1,
            "translation": [
                0,
                0
            ]
        },
        "20180709": {
            "center": [
                160,
                161
            ],
            "radius": 72,
            "rotation_angle": 4.176415502541012,
            "rotation_rad": 0.07289220145067427,
            "scale": 0.8429768805985991,
            "translation": [
                20.80199520181914,
                -23.356903210434638
            ]
        },
        "20181217": {
            "center": [
                159,
                179
            ],
            "matching": [
                103.17057300312064,
                27.995245182742586,
                4.918579171395688
            ],
            "original": [
                103.17057300312064,
                27.995245182742586,
                4.918579171395688
            ],
            "radius": 89,
            "rotation_angle": 0,
            "rotation_rad": 0,
            "scale": 1,
            "translation": [
                0,
                0
            ]
        },
        "20190308": {
            "center": [
                151,
                165
            ],
            "radius": 89,
            "rotation_angle": -9.296082816626042,
            "rotation_rad": -0.1622472526881927,
            "scale": 0.8249147174915916,
            "translation": [
                11.458647682350218,
                -10.819482108720791
            ]
        }
    },
    "10306095_L": {
        "20220307": {
            "center": [
                144,
                126
            ],
            "radius": 107,
            "rotation_angle": 0,
            "rotation_rad": 0,
            "scale": 1,
            "translation": [
                0,
                0
            ]
        }
    },
    "10439969_L": {
        "20200512": {
            "center": [
                153,
                146
            ],
            "radius": 86,
            "rotation_angle": 0,
            "rotation_rad": 0,
            "scale": 1,
            "translation": [
                0,
                0
            ]
        }
    },
    "10713526_R": {},
    "11990421_L": {
        "20210713": {
            "center": [
                116,
                149
            ],
            "radius": 80,
            "rotation_angle": 0,
            "rotation_rad": 0,
            "scale": 1,
            "translation": [
                0,
                0
            ]
        },
        "20220106": {
            "center": [
                107,
                136
            ],
            "radius": 77,
            "rotation_angle": 0,
            "rotation_rad": 0,
            "scale": 1,
            "translation": [
                0,
                0
            ]
        }
    },
    "12291088_L": {},
    "12522028_L": {},
    "12682926_R": {
        "20171225": {
            "center": [
                163,
                123
            ],
            "radius": 81,
            "rotation_angle": 0,
            "rotation_rad": 0,
            "scale": 1,
            "translation": [
                0,
                0
            ]
        },
        "20190625": {
            "center": [
                205,
                147
            ],
            "radius": 95,
            "rotation_angle": 0,
            "rotation_rad": 0,
            "scale": 1,
            "translation": [
                0,
                0
            ]
        }
    },
    "13319575_L": {
        "20220215": {
            "center": [
                159,
                135
            ],
            "radius": 92,
            "rotation_angle": 1.9923480569595065,
            "rotation_rad": 0.03477303343965491,
            "scale": 0.9738123428662308,
            "translation": [
                -2.1443632217058024,
                17.322955537241064
            ]
        }
    },
    "13319575_R": {
        "20220215": {
            "center": [
                165,
                184
            ],
            "radius": 91,
            "rotation_angle": 0,
            "rotation_rad": 0,
            "scale": 1,
            "translation": [
                0,
                0
            ]
        }
    },
    "13790698_L": {
        "20161214": {
            "center": [
                146,
                159
            ],
            "matching": [
                110.61199727932949,
                27.69278126578834,
                4.1701089504510644
            ],
            "original": [
                110.61199727932949,
                27.69278126578834,
                4.1701089504510644
            ],
            "radius": 83,
            "rotation_angle": 0,
            "rotation_rad": 0,
            "scale": 1,
            "translation": [
                0,
                0
            ]
        },
        "20170301": {
            "center": [
                149,
                148
            ],
            "radius": 83,
            "rotation_angle": -9.128535139441695,
            "rotation_rad": -0.15932299406725725,
            "scale": 0.7503819497527174,
            "translation": [
                6.99298470916807,
                -0.9976135562807968
            ]
        },
        "20170405": {
            "center": [
                148,
                142
            ],
            "matching": [
                100.99740727646177,
                28.08770135797927,
                5.22292936171135
            ],
            "original": [
                102.48345876054346,
                28.024265866832895,
                9.72943988133997
            ],
            "radius": 86,
            "rotation_angle": 0.5879737922819602,
            "rotation_rad": 0.01026207859075743,
            "scale": 1.1723399258330969,
            "translation": [
                -10.039672534671148,
                2.755963818820284
            ]
        },
        "20170531": {
            "center": [
                137,
                150
            ],
            "radius": 91,
            "rotation_angle": 2.026938064938428,
            "rotation_rad": 0.0353767429671782,
            "scale": 0.9976774205157092,
            "translation": [
                10.986790185289081,
                -2.2733646774607195
            ]
        },
        "20170621": {
            "center": [
                137,
                144
            ],
            "radius": 82,
            "rotation_angle": 0,
            "rotation_rad": 0,
            "scale": 1,
            "translation": [
                0,
                0
            ]
        },
        "20170726": {
            "center": [
                125,
                155
            ],
            "matching": [
                102.79066045491916,
                28.011267043521887,
                3.9906867892618805
            ],
            "original": [
                102.79066045491916,
                28.011267043521887,
                3.9906867892618805
            ],
            "radius": 89,
            "rotation_angle": 0,
            "rotation_rad": 0,
            "scale": 1,
            "translation": [
                0,
                0
            ]
        },
        "20170809": {
            "center": [
                135,
                150
            ],
            "radius": 83,
            "rotation_angle": 1.0905718566312357,
            "rotation_rad": 0.019034069627802616,
            "scale": 1.043862231445768,
            "translation": [
                12.57174407751765,
                -2.817358430496199
            ]
        },
        "20190709": {
            "center": [
                114,
                143
            ],
            "radius": 84,
            "rotation_angle": 0,
            "rotation_rad": 0,
            "scale": 1,
            "translation": [
                0,
                0
            ]
        },
        "20191231": {
            "center": [
                122,
                140
            ],
            "radius": 77,
            "rotation_angle": 0,
            "rotation_rad": 0,
            "scale": 1,
            "translation": [
                0,
                0
            ]
        }
    },
    "13820694_R": {
        "20211129": {
            "center": [
                144,
                144
            ],
            "matching": [
                100.655091421957,
                28.102446132325444,
                5.3189931909311
            ],
            "original": [
                100.655091421957,
                28.102446132325444,
                5.3189931909311
            ],
            "radius": 127,
            "rotation_angle": 0,
            "rotation_rad": 0,
            "scale": 1,
            "translation": [
                0,
                0
            ]
        }
    },
    "14112463_R": {
        "20201022": {
            "center": [
                148,
                159
            ],
            "matching": [
                101.60897258725093,
                28.061483008228127,
                4.5721247136658105
            ],
            "original": [
                101.36649162039247,
                28.071859454108523,
                4.892298274053716
            ],
            "radius": 96,
            "rotation_angle": -4.71071874925227,
            "rotation_rad": -0.08221755230988127,
            "scale": 1.0471815280256391,
            "translation": [
                -12.20335001471529,
                -10.907625935551991
            ]
        },
        "20210408": {
            "center": [
                178,
                171
            ],
            "radius": 87,
            "rotation_angle": 0,
            "rotation_rad": 0,
            "scale": 1,
            "translation": [
                0,
                0
            ]
        }
    },
    "16006979_R": {},
    "16086122_L": {},
    "16095800_R": {
        "20210930": {
            "center": [
                156,
                148
            ],
            "matching": [
                101.88813451498267,
                28.049567501167544,
                4.327423270601483
            ],
            "original": [
                101.52167332075638,
                28.065215935072082,
                2.6626480698343054
            ],
            "radius": 90,
            "rotation_angle": -1.6777772647513445,
            "rotation_rad": -0.02928273738501556,
            "scale": 0.9200803869800256,
            "translation": [
                -0.9690123910186514,
                3.804649718299153
            ]
        }
    },
    "16710355_R": {},
    "17263001_L": {
        "20170515": {
            "center": [
                164,
                150
            ],
            "matching": [
                93.4515843512126,
                28.42493692187235,
                35.62052149614849
            ],
            "original": [
                99.69196908007316,
                28.144201867557367,
                5.019254846602016
            ],
            "radius": 91,
            "rotation_angle": 0.03785750034176368,
            "rotation_rad": 0.0006607380275386549,
            "scale": 1.0027895842987904,
            "translation": [
                -15.701573426128668,
                9.28152943179208
            ]
        },
        "20170612": {
            "center": [
                157,
                142
            ],
            "radius": 93,
            "rotation_angle": 2.2800770528326177,
            "rotation_rad": 0.03979485177109788,
            "scale": 0.9844967657137796,
            "translation": [
                -2.3073592995180334,
                14.012706815524929
            ]
        },
        "20170816": {
            "center": [
                153,
                155
            ],
            "matching": [
                94.78634942994233,
                28.363345635521497,
                28.57091382157534
            ],
            "original": [
                99.26359114319672,
                28.16290377882266,
                4.496037255303286
            ],
            "radius": 100,
            "rotation_angle": -0.24944235685263483,
            "rotation_rad": -0.004353590421013118,
            "scale": 0.9915304652590595,
            "translation": [
                -4.673630028556474,
                2.464889004081705
            ]
        },
        "20171018": {
            "center": [
                153,
                155
            ],
            "matching": [
                95.77739896064348,
                28.318173221932508,
                24.46852962593606
            ],
            "original": [
                99.2866064237088,
                28.161896939293598,
                4.526129658023794
            ],
            "radius": 100,
            "rotation_angle": 0.19489546817264436,
            "rotation_rad": 0.00340156761682846,
            "scale": 1.0030094568667447,
            "translation": [
                -5.264837175565603,
                1.7209220688293385
            ]
        },
        "20171115": {
            "center": [
                157,
                166
            ],
            "radius": 97,
            "rotation_angle": -1.5714317131218625,
            "rotation_rad": -0.02742665736423148,
            "scale": 1.0049344300092522,
            "translation": [
                -13.675485443038085,
                -6.418491526497547
            ]
        },
        "20171213": {
            "center": [
                162,
                167
            ],
            "radius": 93,
            "rotation_angle": -3.371949922088043,
            "rotation_rad": -0.058851628352802624,
            "scale": 1.0162813621649334,
            "translation": [
                -25.85627480335051,
                -15.59365833561673
            ]
        },
        "20180117": {
            "center": [
                156,
                168
            ],
            "matching": [
                98.32067723508224,
                28.204354995488472,
                1.4605035805128945
            ],
            "original": [
                100.11684140494161,
                28.12573221310501,
                5.027406641077668
            ],
            "radius": 94,
            "rotation_angle": -1.0217912044031243,
            "rotation_rad": -0.0178336207847529,
            "scale": 1.0363418838938567,
            "translation": [
                -13.4654238182058,
                -7.5669174697096935
            ]
        },
        "20180425": {
            "center": [
                146,
                156
            ],
            "matching": [
                94.02017576705359,
                28.39859302118313,
                30.20455519795327
            ],
            "original": [
                98.4135922116253,
                28.200252765133527,
                4.370873236939087
            ],
            "radius": 92,
            "rotation_angle": 0.2993041600770271,
            "rotation_rad": 0.005223843058260288,
            "scale": 1.009366759690088,
            "translation": [
                2.2924946746161936,
                0.5971127212464324
            ]
        }
    },
    "17634105_R": {
        "20170503": {
            "center": [
                148,
                152
            ],
            "radius": 102,
            "rotation_angle": 0,
            "rotation_rad": 0,
            "scale": 1,
            "translation": [
                0,
                0
            ]
        },
        "20170531": {
            "center": [
                157,
                152
            ],
            "radius": 88,
            "rotation_angle": 0,
            "rotation_rad": 0,
            "scale": 1,
            "translation": [
                0,
                0
            ]
        },
        "20170705": {
            "center": [
                137,
                154
            ],
            "radius": 96,
            "rotation_angle": 0,
            "rotation_rad": 0,
            "scale": 1,
            "translation": [
                0,
                0
            ]
        },
        "20170830": {
            "center": [
                154,
                155
            ],
            "radius": 91,
            "rotation_angle": 0,
            "rotation_rad": 0,
            "scale": 1,
            "translation": [
                0,
                0
            ]
        }
    },
    "17768873_R": {},
    "18289838_L": {},
    "20256047_L": {
        "20210818": {
            "center": [
                155,
                158
            ],
            "radius": 96,
            "rotation_angle": -3.526647644952526,
            "rotation_rad": -0.061551612962125565,
            "scale": 0.99290490176945,
            "translation": [
                -14.849494623218284,
                -4.127983301024059
            ]
        }
    },
    "20256047_R": {
        "20210630": {
            "center": [
                157,
                155
            ],
            "radius": 86,
            "rotation_angle": -2.597133252281193,
            "rotation_rad": -0.04532852636533535,
            "scale": 1.0500837545112245,
            "translation": [
                9.658840176931832,
                5.553537923773803
            ]
        },
        "20210818": {
            "center": [
                157,
                155
            ],
            "radius": 87,
            "rotation_angle": -2.156328022505455,
            "rotation_rad": -0.03763502374573858,
            "scale": 1.0201766922577402,
            "translation": [
                9.792757228201125,
                2.0759894346643932
            ]
        }
    },
    "20307089_R": {
        "20210720": {
            "center": [
                145,
                142
            ],
            "matching": [
                99.69260945148451,
                28.144173970738827,
                13.93173529920838
            ],
            "original": [
                99.34966146667277,
                28.15913969275186,
                6.105274719507258
            ],
            "radius": 88,
            "rotation_angle": 0.02820671632317746,
            "rotation_rad": 0.0004923000710154756,
            "scale": 1.0054465050455519,
            "translation": [
                1.0894891389782373,
                -0.05198365104146063
            ]
        }
    },
    "20342007_L": {
        "20211123": {
            "center": [
                153,
                130
            ],
            "radius": 97,
            "rotation_angle": 4.94732240938666,
            "rotation_rad": 0.08634706520149604,
            "scale": 1.0569620722669444,
            "translation": [
                -1.3276161950471987,
                -4.720212162411563
            ]
        }
    },
    "20354860_R": {
        "20211108": {
            "center": [
                157,
                145
            ],
            "matching": [
                105.11664159417447,
                27.914088838464345,
                2.3722232027609156
            ],
            "original": [
                105.11664159417447,
                27.914088838464345,
                2.3722232027609156
            ],
            "radius": 77,
            "rotation_angle": 0,
            "rotation_rad": 0,
            "scale": 1,
            "translation": [
                0,
                0
            ]
        }
    },
    "20402196_L": {},
    "20724856_R": {},
    "20724924_R": {
        "20211209": {
            "center": [
                160,
                135
            ],
            "radius": 83,
            "rotation_angle": -1.4221792384131953,
            "rotation_rad": -0.024821710263815674,
            "scale": 0.9174697075521894,
            "translation": [
                5.968696883880952,
                -2.519660254709329
            ]
        }
    },
    "20770192_L": {
        "20211224": {
            "center": [
                148,
                140
            ],
            "matching": [
                99.37716139160145,
                28.157937734651416,
                4.285505786447918
            ],
            "original": [
                98.88692661079945,
                28.17941481566833,
                4.20610957299263
            ],
            "radius": 88,
            "rotation_angle": -3.544808215601196,
            "rotation_rad": -0.0618685747139859,
            "scale": 0.9759434039829304,
            "translation": [
                -5.005641377259188,
                3.5872737074185466
            ]
        }
    },
    "20770192_R": {
        "20211224": {
            "center": [
                153,
                163
            ],
            "matching": [
                100.58787621673855,
                28.10534722190431,
                4.1400022865147355
            ],
            "original": [
                101.4194301067666,
                28.06959195024641,
                4.118749159146713
            ],
            "radius": 99,
            "rotation_angle": 3.3138515020368646,
            "rotation_rad": 0.05783761963270286,
            "scale": 1.011045594387828,
            "translation": [
                13.324977122216197,
                -29.982130227072624
            ]
        }
    }
}