{
    "00006202_R": {
        "20221026": {
            "center": [
                155,
                156
            ],
            "radius": 104,
            "rotation_angle": 0,
            "rotation_rad": 0,
            "scale": 1,
            "translation": [
                0,
                0
            ]
        },
        "20230712": {
            "center": [
                104,
                160
            ],
            "matching": [
                96.41662782467588,
                28.2892842292177,
                7.681913705894557
            ],
            "original": [
                98.22442039118201,
                28.208608860886123,
                6.827729653111077
            ],
            "radius": 98,
            "rotation_angle": -57.67744440501694,
            "rotation_rad": -1.0066613090035275,
            "scale": 1.2211902124848453,
            "translation": [
                43.648777725583045,
                125.5345086517417
            ]
        },
        "20230920": {
            "center": [
                165,
                155
            ],
            "matching": [
                100.79593726326422,
                28.096373333189618,
                6.769307701444532
            ],
            "original": [
                101.69366740551612,
                28.057864511749422,
                5.455541165651965
            ],
            "radius": 111,
            "rotation_angle": -7.635560219707145,
            "rotation_rad": -0.1332656660681913,
            "scale": 0.7483860856181078,
            "translation": [
                88.81825479502646,
                -18.067101673518817
            ]
        }
    },
    "00016302_R": {
        "20210901": {
            "center": [
                156,
                150
            ],
            "matching": [
                98.59211894248504,
                28.19238160293688,
                7.318460945634875
            ],
            "original": [
                107.4340394611816,
                27.819384555941316,
                8.136802055171833
            ],
            "radius": 112,
            "rotation_angle": -5.172653191873029,
            "rotation_rad": -0.09027982926197835,
            "scale": 1.0692209189599318,
            "translation": [
                -18.56383327632588,
                7.964449738894132
            ]
        },
        "20220509": {
            "center": [
                169,
                138
            ],
            "matching": [
                100.73294714774357,
                28.099088205606627,
                7.988499352316598
            ],
            "original": [
                101.85833609180183,
                28.050837833930665,
                3.4138397537907865
            ],
            "radius": 103,
            "rotation_angle": -7.596457586123029,
            "rotation_rad": -0.13258319636594756,
            "scale": 0.9429337390630259,
            "translation": [
                -11.422962113135213,
                0.6570055492018625
            ]
        },
        "20220926": {
            "center": [
                148,
                145
            ],
            "radius": 100,
            "rotation_angle": 0,
            "rotation_rad": 0,
            "scale": 1,
            "translation": [
                0,
                0
            ]
        }
    },
    "00200499_R": {
        "20210531": {
            "center": [
                160,
                142
            ],
            "radius": 103,
            "rotation_angle": 0,
            "rotation_rad": 0,
            "scale": 1,
            "translation": [
                0,
                0
            ]
        },
        "20220124": {
            "center": [
                167,
                155
            ],
            "radius": 115,
            "rotation_angle": 0,
            "rotation_rad": 0,
            "scale": 1,
            "translation": [
                0,
                0
            ]
        },
        "20220803": {
            "center": [
                182,
                148
            ],
            "radius": 122,
            "rotation_angle": 0,
            "rotation_rad": 0,
            "scale": 1,
            "translation": [
                0,
                0
            ]
        }
    },
    "00294362_R": {
        "20211125": {
            "center": [
                166,
                144
            ],
            "radius": 119,
            "rotation_angle": 0,
            "rotation_rad": 0,
            "scale": 1,
            "translation": [
                0,
                0
            ]
        },
        "20220616": {
            "center": [
                167,
                143
            ],
            "radius": 98,
            "rotation_angle": 0,
            "rotation_rad": 0,
            "scale": 1,
            "translation": [
                0,
                0
            ]
        },
        "20221222": {
            "center": [
                179,
                157
            ],
            "radius": 125,
            "rotation_angle": 0,
            "rotation_rad": 0,
            "scale": 1,
            "translation": [
                0,
                0
            ]
        }
    },
    "00367827_L": {
        "20220622": {
            "center": [
                136,
                179
            ],
            "radius": 125,
            "rotation_angle": 0,
            "rotation_rad": 0,
            "scale": 1,
            "translation": [
                0,
                0
            ]
        },
        "20230308": {
            "center": [
                146,
                157
            ],
            "radius": 125,
            "rotation_angle": 0,
            "rotation_rad": 0,
            "scale": 1,
            "translation": [
                0,
                0
            ]
        }
    },
    "00367827_R": {
        "20220622": {
            "center": [
                136,
                143
            ],
            "radius": 103,
            "rotation_angle": 0,
            "rotation_rad": 0,
            "scale": 1,
            "translation": [
                0,
                0
            ]
        },
        "20230308": {
            "center": [
                145,
                179
            ],
            "radius": 103,
            "rotation_angle": 0,
            "rotation_rad": 0,
            "scale": 1,
            "translation": [
                0,
                0
            ]
        }
    },
    "00468301_L": {
        "20211004": {
            "center": [
                152,
                145
            ],
            "matching": [
                101.90736237757514,
                28.04874799781494,
                2.5014180835868163
            ],
            "original": [
                103.55521783181358,
                27.979083743118057,
                3.6782379895861355
            ],
            "radius": 93,
            "rotation_angle": 5.1364296172839365,
            "rotation_rad": 0.08964760861855693,
            "scale": 1.0274755389853742,
            "translation": [
                12.321491754639084,
                -11.199832008643774
            ]
        },
        "20220502": {
            "center": [
                154,
                164
            ],
            "matching": [
                101.05395962732919,
                28.08527025593447,
                9.017942967511368
            ],
            "original": [
                102.98645871392036,
                28.003002360892815,
                3.035044047745035
            ],
            "radius": 98,
            "rotation_angle": 1.6343397284797918,
            "rotation_rad": 0.028524609358122507,
            "scale": 1.0121673863552392,
            "translation": [
                3.696847711244075,
                -21.2574932633014
            ]
        },
        "20221024": {
            "center": [
                149,
                138
            ],
            "matching": [
                98.79509982055998,
                28.18344956499584,
                11.135859460710574
            ],
            "original": [
                100.91156654515908,
                28.091394126801553,
                3.4088518447594023
            ],
            "radius": 87,
            "rotation_angle": 1.2508551096262641,
            "rotation_rad": 0.021831540128372927,
            "scale": 0.998897388088427,
            "translation": [
                6.935795894398495,
                4.590609247977625
            ]
        }
    },
    "01244637_L": {
        "20220408": {
            "center": [
                150,
                157
            ],
            "matching": [
                97.54932065977076,
                28.238561115837108,
                10.946610757166654
            ],
            "original": [
                99.5161196533408,
                28.151869272630936,
                6.120177677356876
            ],
            "radius": 105,
            "rotation_angle": -2.257001451337116,
            "rotation_rad": -0.039392106548123244,
            "scale": 1.0137368801536057,
            "translation": [
                -8.647903686857667,
                -6.305905622223143
            ]
        },
        "20220624": {
            "center": [
                155,
                148
            ],
            "matching": [
                99.95786532550991,
                28.13263387995839,
                4.765938471506577
            ],
            "original": [
                101.30716960044705,
                28.07440179004879,
                5.544555617571238
            ],
            "radius": 99,
            "rotation_angle": 2.4535189153292953,
            "rotation_rad": 0.042821983332456175,
            "scale": 1.1718380945076747,
            "translation": [
                -23.532295703788485,
                -7.090153228634989
            ]
        },
        "20220902": {
            "center": [
                155,
                153
            ],
            "matching": [
                101.39030917206813,
                28.070839135059064,
                4.523874842965816
            ],
            "original": [
                99.79181609800503,
                28.139854345025167,
                4.51149716799306
            ],
            "radius": 95,
            "rotation_angle": 0.46133195569360747,
            "rotation_rad": 0.008051761571518051,
            "scale": 1.306081255523384,
            "translation": [
                -26.745906761827847,
                -11.411395732149586
            ]
        },
        "20221125": {
            "center": [
                149,
                146
            ],
            "matching": [
                100.3710699316604,
                28.114718072178682,
                6.185895145700702
            ],
            "original": [
                101.27592518384543,
                28.07574141592847,
                4.266757795185602
            ],
            "radius": 110,
            "rotation_angle": -6.610896786281265,
            "rotation_rad": -0.11538191543011997,
            "scale": 1.2128026861106453,
            "translation": [
                -40.82018293684386,
                -10.334456856825607
            ]
        },
        "20230913": {
            "center": [
                153,
                151
            ],
            "radius": 100,
            "rotation_angle": 0,
            "rotation_rad": 0,
            "scale": 1,
            "translation": [
                0,
                0
            ]
        }
    },
    "01790839_L": {
        "20211102": {
            "center": [
                166,
                144
            ],
            "radius": 138,
            "rotation_angle": 0,
            "rotation_rad": 0,
            "scale": 1,
            "translation": [
                0,
                0
            ]
        },
        "20220804": {
            "center": [
                147,
                124
            ],
            "radius": 124,
            "rotation_angle": 0,
            "rotation_rad": 0,
            "scale": 1,
            "translation": [
                0,
                0
            ]
        }
    },
    "01790839_R": {
        "20211102": {
            "center": [
                21,
                253
            ],
            "matching": [
                99.3395985280832,
                28.159579603666526,
                4.657174199865961
            ],
            "original": [
                99.3395985280832,
                28.159579603666526,
                4.657174199865961
            ],
            "radius": 21,
            "rotation_angle": 0,
            "rotation_rad": 0,
            "scale": 1,
            "translation": [
                0,
                0
            ]
        },
        "20220804": {
            "center": [
                151,
                147
            ],
            "matching": [
                99.80514318949758,
                28.13927438806347,
                3.9121386956302233
            ],
            "original": [
                100.02210158976348,
                28.129843854888065,
                4.259796378902345
            ],
            "radius": 89,
            "rotation_angle": 8.690180250252892,
            "rotation_rad": 0.15167225795869774,
            "scale": 1.0342860957921851,
            "translation": [
                -30.3384627986264,
                -16.196815451691492
            ]
        }
    },
    "01979334_R": {
        "20221227": {
            "center": [
                165,
                151
            ],
            "matching": [
                99.2252103096474,
                28.16458332792639,
                10.268630991648497
            ],
            "original": [
                100.90228432074458,
                28.091793625530563,
                3.7722959084692045
            ],
            "radius": 91,
            "rotation_angle": 1.770697828703759,
            "rotation_rad": 0.03090450716879515,
            "scale": 1.0452231937784306,
            "translation": [
                -3.2543843982375478,
                -10.051004155261595
            ]
        },
        "20230921": {
            "center": [
                142,
                137
            ],
            "radius": 107,
            "rotation_angle": 0,
            "rotation_rad": 0,
            "scale": 1,
            "translation": [
                0,
                0
            ]
        }
    },
    "02062686_L": {
        "20220428": {
            "center": [
                147,
                156
            ],
            "radius": 102,
            "rotation_angle": 0,
            "rotation_rad": 0,
            "scale": 1,
            "translation": [
                0,
                0
            ]
        }
    },
    "02236052_R": {
        "20211129": {
            "center": [
                158,
                109
            ],
            "radius": 109,
            "rotation_angle": 0,
            "rotation_rad": 0,
            "scale": 1,
            "translation": [
                0,
                0
            ]
        },
        "20220401": {
            "center": [
                147,
                126
            ],
            "radius": 93,
            "rotation_angle": 0,
            "rotation_rad": 0,
            "scale": 1,
            "translation": [
                0,
                0
            ]
        },
        "20220624": {
            "center": [
                147,
                136
            ],
            "radius": 96,
            "rotation_angle": 0,
            "rotation_rad": 0,
            "scale": 1,
            "translation": [
                0,
                0
            ]
        },
        "20220902": {
            "center": [
                142,
                150
            ],
            "radius": 109,
            "rotation_angle": 0,
            "rotation_rad": 0,
            "scale": 1,
            "translation": [
                0,
                0
            ]
        },
        "20221125": {
            "center": [
                162,
                153
            ],
            "radius": 92,
            "rotation_angle": 0,
            "rotation_rad": 0,
            "scale": 1,
            "translation": [
                0,
                0
            ]
        },
        "20230310": {
            "center": [
                220,
                44
            ],
            "radius": 44,
            "rotation_angle": 0,
            "rotation_rad": 0,
            "scale": 1,
            "translation": [
                0,
                0
            ]
        },
        "20230519": {
            "center": [
                78,
                160
            ],
            "radius": 78,
            "rotation_angle": 0,
            "rotation_rad": 0,
            "scale": 1,
            "translation": [
                0,
                0
            ]
        }
    },
    "02408215_L": {
        "20230627": {
            "center": [
                139,
                167
            ],
            "radius": 103,
            "rotation_angle": 0,
            "rotation_rad": 0,
            "scale": 1,
            "translation": [
                0,
                0
            ]
        }
    },
    "02522650_R": {
        "20230620": {
            "center": [
                156,
                134
            ],
            "radius": 108,
            "rotation_angle": 0,
            "rotation_rad": 0,
            "scale": 1,
            "translation": [
                0,
                0
            ]
        }
    },
    "02875773_L": {
        "20220420": {
            "center": [
                145,
                149
            ],
            "matching": [
                96.87294547642661,
                28.268778559621897,
                32.97221170224714
            ],
            "original": [
                103.34070268884902,
                27.988089505631244,
                4.114008892605506
            ],
            "radius": 111,
            "rotation_angle": -0.17681611293648422,
            "rotation_rad": -0.003086023341319789,
            "scale": 1.0237265301688963,
            "translation": [
                -1.0903169187721744,
                -6.666156543493955
            ]
        },
        "20230323": {
            "center": [
                152,
                138
            ],
            "matching": [
                99.91928911526962,
                28.134310253178235,
                12.909215708118982
            ],
            "original": [
                101.72409478463072,
                28.056565269952195,
                2.6784833493362687
            ],
            "radius": 104,
            "rotation_angle": -1.8832342026670563,
            "rotation_rad": -0.03286863742271031,
            "scale": 0.997513517466274,
            "translation": [
                -9.86637380500489,
                -1.988920351725696
            ]
        }
    },
    "03048783_L": {
        "20230307": {
            "center": [
                146,
                144
            ],
            "matching": [
                97.65023429281821,
                28.23407071237319,
                8.369771208309134
            ],
            "original": [
                100.55232141149469,
                28.10688259435253,
                6.22090919443167
            ],
            "radius": 104,
            "rotation_angle": 4.515912308577038,
            "rotation_rad": 0.07881753851600747,
            "scale": 0.9892298715230781,
            "translation": [
                2.0114245707339435,
                6.561007574443636
            ]
        }
    },
    "03270708_R": {
        "20230608": {
            "center": [
                149,
                142
            ],
            "matching": [
                99.04126411360727,
                28.17264186036975,
                7.953699517116208
            ],
            "original": [
                97.99601908974508,
                28.21871927241463,
                4.334282982541461
            ],
            "radius": 105,
            "rotation_angle": -3.7474521438532125,
            "rotation_rad": -0.06540537847115874,
            "scale": 1.007782843604824,
            "translation": [
                -6.802371137266064,
                21.358431881170695
            ]
        }
    },
    "03314482_R": {
        "20220418": {
            "center": [
                164,
                160
            ],
            "radius": 104,
            "rotation_angle": 0,
            "rotation_rad": 0,
            "scale": 1,
            "translation": [
                0,
                0
            ]
        }
    },
    "03346458_R": {
        "20230816": {
            "center": [
                158,
                144
            ],
            "radius": 107,
            "rotation_angle": 0,
            "rotation_rad": 0,
            "scale": 1,
            "translation": [
                0,
                0
            ]
        }
    },
    "03368010_R": {
        "20230307": {
            "center": [
                150,
                148
            ],
            "radius": 105,
            "rotation_angle": 0,
            "rotation_rad": 0,
            "scale": 1,
            "translation": [
                0,
                0
            ]
        }
    },
    "03408585_R": {
        "20210929": {
            "center": [
                159,
                144
            ],
            "radius": 110,
            "rotation_angle": 0,
            "rotation_rad": 0,
            "scale": 1,
            "translation": [
                0,
                0
            ]
        }
    },
    "03709937_R": {
        "20230208": {
            "center": [
                152,
                145
            ],
            "matching": [
                97.2179006027522,
                28.253341225133056,
                14.734944622235663
            ],
            "original": [
                104.54298874104401,
                27.937854490435313,
                5.539645623073813
            ],
            "radius": 104,
            "rotation_angle": -2.4183677482108332,
            "rotation_rad": -0.04220847973032024,
            "scale": 0.9512554516587096,
            "translation": [
                4.527821133728288,
                10.00651999926999
            ]
        }
    },
    "03936787_L": {
        "20230530": {
            "center": [
                147,
                147
            ],
            "radius": 133,
            "rotation_angle": 0,
            "rotation_rad": 0,
            "scale": 1,
            "translation": [
                0,
                0
            ]
        }
    },
    "03959415_L": {
        "20221124": {
            "center": [
                151,
                173
            ],
            "radius": 131,
            "rotation_angle": 0,
            "rotation_rad": 0,
            "scale": 1,
            "translation": [
                0,
                0
            ]
        }
    },
    "03959415_R": {
        "20221124": {
            "center": [
                112,
                119
            ],
            "radius": 112,
            "rotation_angle": 0,
            "rotation_rad": 0,
            "scale": 1,
            "translation": [
                0,
                0
            ]
        }
    },
    "03978730_R": {
        "20211124": {
            "center": [
                151,
                142
            ],
            "matching": [
                96.13639959317437,
                28.301925075447695,
                20.738683314044213
            ],
            "original": [
                96.49542321166234,
                28.285736456697855,
                0.8789699920461439
            ],
            "radius": 106,
            "rotation_angle": 0.0719476122738597,
            "rotation_rad": 0.001255722723127136,
            "scale": 0.9550298141149253,
            "translation": [
                4.493166965634288,
                -1.6472531117912155
            ]
        },
        "20220704": {
            "center": [
                166,
                135
            ],
            "matching": [
                99.52214548328351,
                28.151606309658263,
                5.652599232410371
            ],
            "original": [
                94.11163797546645,
                28.394370286627435,
                6.122884177313432
            ],
            "radius": 104,
            "rotation_angle": 21.79794083001316,
            "rotation_rad": 0.38044583763863526,
            "scale": 1.048803531489885,
            "translation": [
                -9.708849871176866,
                32.681655113870995
            ]
        }
    },
    "04770769_R": {
        "20220908": {
            "center": [
                172,
                145
            ],
            "radius": 97,
            "rotation_angle": 0,
            "rotation_rad": 0,
            "scale": 1,
            "translation": [
                0,
                0
            ]
        },
        "20230131": {
            "center": [
                94,
                94
            ],
            "radius": 94,
            "rotation_angle": 0,
            "rotation_rad": 0,
            "scale": 1,
            "translation": [
                0,
                0
            ]
        }
    },
    "04851616_R": {
        "20211216": {
            "center": [
                163,
                154
            ],
            "matching": [
                97.75937759880946,
                28.229219329680305,
                13.136438160755059
            ],
            "original": [
                99.05054274084125,
                28.172235012991827,
                11.152358333300322
            ],
            "radius": 96,
            "rotation_angle": -1.0497947329642932,
            "rotation_rad": -0.018322374560321566,
            "scale": 0.9697048477058138,
            "translation": [
                2.952163082592932,
                -3.834756351785309
            ]
        },
        "20220526": {
            "center": [
                164,
                157
            ],
            "matching": [
                97.10761023778446,
                28.25827094350594,
                21.491196015724054
            ],
            "original": [
                98.98512002724023,
                28.17510446833584,
                6.846861937057788
            ],
            "radius": 119,
            "rotation_angle": -0.28885986630565014,
            "rotation_rad": -0.0050415557439042235,
            "scale": 0.9997178589777944,
            "translation": [
                4.36918971279146,
                -4.691326415152311
            ]
        }
    },
    "05084585_L": {
        "20210930": {
            "center": [
                121,
                132
            ],
            "matching": [
                97.3803475862069,
                28.24609040498842,
                5.417731387419287
            ],
            "original": [
                97.3803475862069,
                28.24609040498842,
                5.417731387419287
            ],
            "radius": 115,
            "rotation_angle": 0,
            "rotation_rad": 0,
            "scale": 1,
            "translation": [
                0,
                0
            ]
        },
        "20220526": {
            "center": [
                165,
                175
            ],
            "radius": 104,
            "rotation_angle": 0,
            "rotation_rad": 0,
            "scale": 1,
            "translation": [
                0,
                0
            ]
        }
    },
    "05120074_L": {
        "20210721": {
            "center": [
                154,
                165
            ],
            "matching": [
                96.74854420918766,
                28.27435922026298,
                6.185645930872922
            ],
            "original": [
                93.1861627362174,
                28.437289323492976,
                7.080298345073485
            ],
            "radius": 114,
            "rotation_angle": -2.215094533889719,
            "rotation_rad": -0.038660692859304714,
            "scale": 1.004289226434585,
            "translation": [
                -7.408491679707048,
                0.30840017166082134
            ]
        },
        "20220117": {
            "center": [
                156,
                172
            ],
            "matching": [
                98.94116162774694,
                28.17703355935776,
                5.02909645508277
            ],
            "original": [
                98.07527412029178,
                28.215208302120036,
                5.097186466394241
            ],
            "radius": 89,
            "rotation_angle": -2.997504527927235,
            "rotation_rad": -0.052316323355768565,
            "scale": 1.0097517274924932,
            "translation": [
                -6.6678833814779,
                -4.875368411889141
            ]
        },
        "20220808": {
            "center": [
                141,
                157
            ],
            "matching": [
                98.4199714013346,
                28.199971263661944,
                5.011597391506062
            ],
            "original": [
                97.73703527168732,
                28.230211997451725,
                5.496950573871055
            ],
            "radius": 104,
            "rotation_angle": -4.021892120711406,
            "rotation_rad": -0.07019525966643125,
            "scale": 0.9861167808077345,
            "translation": [
                14.895083481230188,
                15.243811117451258
            ]
        }
    },
    "05655586_L": {
        "20220208": {
            "center": [
                128,
                214
            ],
            "radius": 90,
            "rotation_angle": 0,
            "rotation_rad": 0,
            "scale": 1,
            "translation": [
                0,
                0
            ]
        }
    },
    "05701544_L": {
        "20220629": {
            "center": [
                195,
                77
            ],
            "matching": [
                100.05865493567953,
                28.128257003970592,
                4.061089216746596
            ],
            "original": [
                99.29564087182564,
                28.161501776984753,
                5.516098593643994
            ],
            "radius": 77,
            "rotation_angle": 16.19825070741492,
            "rotation_rad": 0.28271280790789105,
            "scale": 1.159262112889952,
            "translation": [
                -109.18307174352931,
                76.16342411725795
            ]
        },
        "20221228": {
            "center": [
                177,
                184
            ],
            "matching": [
                99.04148660328435,
                28.172632104241195,
                8.83130276687629
            ],
            "original": [
                99.19191311863516,
                28.166040942693243,
                4.471919894862266
            ],
            "radius": 91,
            "rotation_angle": 7.056607656851016,
            "rotation_rad": 0.12316103763349241,
            "scale": 1.1026425880881043,
            "translation": [
                -111.95442312763839,
                -26.524493846601075
            ]
        },
        "20230308": {
            "center": [
                176,
                186
            ],
            "radius": 118,
            "rotation_angle": 0,
            "rotation_rad": 0,
            "scale": 1,
            "translation": [
                0,
                0
            ]
        }
    },
    "06271674_L": {
        "20211224": {
            "center": [
                189,
                137
            ],
            "radius": 102,
            "rotation_angle": 0,
            "rotation_rad": 0,
            "scale": 1,
            "translation": [
                0,
                0
            ]
        },
        "20220729": {
            "center": [
                159,
                115
            ],
            "radius": 105,
            "rotation_angle": 0,
            "rotation_rad": 0,
            "scale": 1,
            "translation": [
                0,
                0
            ]
        },
        "20221125": {
            "center": [
                161,
                150
            ],
            "radius": 107,
            "rotation_angle": 0,
            "rotation_rad": 0,
            "scale": 1,
            "translation": [
                0,
                0
            ]
        },
        "20230918": {
            "center": [
                118,
                122
            ],
            "radius": 118,
            "rotation_angle": 0,
            "rotation_rad": 0,
            "scale": 1,
            "translation": [
                0,
                0
            ]
        }
    },
    "06387643_R": {
        "20210809": {
            "center": [
                141,
                185
            ],
            "radius": 119,
            "rotation_angle": 0,
            "rotation_rad": 0,
            "scale": 1,
            "translation": [
                0,
                0
            ]
        },
        "20220307": {
            "center": [
                138,
                197
            ],
            "radius": 107,
            "rotation_angle": 0,
            "rotation_rad": 0,
            "scale": 1,
            "translation": [
                0,
                0
            ]
        },
        "20220502": {
            "center": [
                160,
                140
            ],
            "radius": 133,
            "rotation_angle": 0,
            "rotation_rad": 0,
            "scale": 1,
            "translation": [
                0,
                0
            ]
        },
        "20221003": {
            "center": [
                158,
                146
            ],
            "radius": 111,
            "rotation_angle": 0,
            "rotation_rad": 0,
            "scale": 1,
            "translation": [
                0,
                0
            ]
        },
        "20221229": {
            "center": [
                155,
                141
            ],
            "radius": 138,
            "rotation_angle": 0,
            "rotation_rad": 0,
            "scale": 1,
            "translation": [
                0,
                0
            ]
        }
    },
    "06626994_R": {
        "20230601": {
            "center": [
                157,
                122
            ],
            "radius": 108,
            "rotation_angle": 0,
            "rotation_rad": 0,
            "scale": 1,
            "translation": [
                0,
                0
            ]
        }
    },
    "06835029_R": {
        "20230815": {
            "center": [
                155,
                165
            ],
            "radius": 128,
            "rotation_angle": 0,
            "rotation_rad": 0,
            "scale": 1,
            "translation": [
                0,
                0
            ]
        }
    },
    "07256061_L": {
        "20230118": {
            "center": [
                154,
                127
            ],
            "matching": [
                98.48980514876659,
                28.196890826218638,
                5.546351151674279
            ],
            "original": [
                99.44403833459648,
                28.155016085607482,
                5.2180073930333934
            ],
            "radius": 113,
            "rotation_angle": 0.2600564440605676,
            "rotation_rad": 0.004538841189885357,
            "scale": 0.9142790648384619,
            "translation": [
                -31.017634641807838,
                -14.35738575842418
            ]
        }
    },
    "07256061_R": {
        "20230118": {
            "center": [
                244,
                68
            ],
            "radius": 60,
            "rotation_angle": 0,
            "rotation_rad": 0,
            "scale": 1,
            "translation": [
                0,
                0
            ]
        }
    },
    "07425712_L": {
        "20230307": {
            "center": [
                133,
                177
            ],
            "radius": 103,
            "rotation_angle": 0,
            "rotation_rad": 0,
            "scale": 1,
            "translation": [
                0,
                0
            ]
        },
        "20230418": {
            "center": [
                151,
                156
            ],
            "matching": [
                101.01226156392322,
                28.087062662304376,
                4.331183342280584
            ],
            "original": [
                100.74643327413958,
                28.098506811096428,
                4.6737711517001745
            ],
            "radius": 110,
            "rotation_angle": -2.34829955973135,
            "rotation_rad": -0.040985559140445306,
            "scale": 0.888472363170783,
            "translation": [
                -3.355741580613703,
                -2.067796533869398
            ]
        },
        "20230815": {
            "center": [
                145,
                159
            ],
            "matching": [
                99.72786898714244,
                28.142638218538238,
                6.707317817547587
            ],
            "original": [
                103.88176253919569,
                27.965410512684322,
                5.72546670877537
            ],
            "radius": 100,
            "rotation_angle": 12.521485489530829,
            "rotation_rad": 0.21854114903300692,
            "scale": 1.1290097321484922,
            "translation": [
                -1.9527425523522268,
                -6.79198491693591
            ]
        }
    },
    "07535628_R": {
        "20230103": {
            "center": [
                153,
                143
            ],
            "matching": [
                99.29563357327176,
                28.16150209620539,
                17.90361391617267
            ],
            "original": [
                101.89867128434967,
                28.049118398412407,
                2.721033346648653
            ],
            "radius": 117,
            "rotation_angle": -0.9002950646428087,
            "rotation_rad": -0.0157131131174722,
            "scale": 0.9991793330352114,
            "translation": [
                -12.912563155265172,
                5.941783296348213
            ]
        },
        "20230912": {
            "center": [
                155,
                137
            ],
            "radius": 103,
            "rotation_angle": 0,
            "rotation_rad": 0,
            "scale": 1,
            "translation": [
                0,
                0
            ]
        }
    },
    "07557293_L": {
        "20230613": {
            "center": [
                152,
                154
            ],
            "matching": [
                98.94773653912026,
                28.176744968359884,
                9.417397115004823
            ],
            "original": [
                99.91768228677502,
                28.134380093783168,
                6.715344452109662
            ],
            "radius": 106,
            "rotation_angle": 1.7942845350490164,
            "rotation_rad": 0.03131617285422093,
            "scale": 1.0648067692507532,
            "translation": [
                -4.468870429877789,
                -5.506404723240941
            ]
        },
        "20230725": {
            "center": [
                146,
                142
            ],
            "matching": [
                99.97652195116287,
                28.13182336709906,
                15.364856418183532
            ],
            "original": [
                102.17945264331247,
                28.03716788951747,
                3.180336801847149
            ],
            "radius": 138,
            "rotation_angle": -2.4134242478016565,
            "rotation_rad": -0.042122199371606425,
            "scale": 0.9378755950863126,
            "translation": [
                8.826435806744513,
                4.340197968292195
            ]
        }
    },
    "07557293_R": {
        "20230613": {
            "center": [
                162,
                150
            ],
            "matching": [
                99.13317985893417,
                28.168613237601065,
                6.1387957557392046
            ],
            "original": [
                97.42956504702194,
                28.243895971264678,
                5.557657049787848
            ],
            "radius": 109,
            "rotation_angle": 3.4015320625027097,
            "rotation_rad": 0.059367934102825835,
            "scale": 1.0726908189572602,
            "translation": [
                -1.22710149788103,
                -9.502489664731748
            ]
        },
        "20230725": {
            "center": [
                158,
                154
            ],
            "radius": 144,
            "rotation_angle": 0,
            "rotation_rad": 0,
            "scale": 1,
            "translation": [
                0,
                0
            ]
        }
    },
    "07622974_L": {
        "20230615": {
            "center": [
                140,
                211
            ],
            "radius": 93,
            "rotation_angle": 0,
            "rotation_rad": 0,
            "scale": 1,
            "translation": [
                0,
                0
            ]
        }
    },
    "07838199_L": {
        "20220328": {
            "center": [
                141,
                172
            ],
            "matching": [
                99.5998516574428,
                28.148216692755568,
                2.217655627850559
            ],
            "original": [
                99.40361727620243,
                28.156781723004723,
                4.907663267696849
            ],
            "radius": 99,
            "rotation_angle": -2.131218461022455,
            "rotation_rad": -0.03719677922412827,
            "scale": 1.0176731719706973,
            "translation": [
                -9.04267912943125,
                -3.7157085611338516
            ]
        },
        "20221205": {
            "center": [
                131,
                178
            ],
            "radius": 126,
            "rotation_angle": 0,
            "rotation_rad": 0,
            "scale": 1,
            "translation": [
                0,
                0
            ]
        }
    },
    "08005295_R": {
        "20220608": {
            "center": [
                42,
                275
            ],
            "radius": 29,
            "rotation_angle": 0,
            "rotation_rad": 0,
            "scale": 1,
            "translation": [
                0,
                0
            ]
        }
    },
    "10006476_L": {
        "20211103": {
            "center": [
                113,
                188
            ],
            "matching": [
                97.24991874474642,
                28.251911137362114,
                11.193509914235998
            ],
            "original": [
                98.135668254413,
                28.21253476722957,
                6.376330088375269
            ],
            "radius": 113,
            "rotation_angle": -0.722147486197545,
            "rotation_rad": -0.012603851319147466,
            "scale": 1.008455951740509,
            "translation": [
                -1.7407030267360435,
                -1.4267065428734895
            ]
        },
        "20220622": {
            "center": [
                138,
                139
            ],
            "radius": 138,
            "rotation_angle": 0,
            "rotation_rad": 0,
            "scale": 1,
            "translation": [
                0,
                0
            ]
        },
        "20221014": {
            "center": [
                156,
                144
            ],
            "radius": 144,
            "rotation_angle": 0,
            "rotation_rad": 0,
            "scale": 1,
            "translation": [
                0,
                0
            ]
        },
        "20230210": {
            "center": [
                176,
                182
            ],
            "radius": 122,
            "rotation_angle": 0,
            "rotation_rad": 0,
            "scale": 1,
            "translation": [
                0,
                0
            ]
        }
    },
    "10006476_R": {
        "20211103": {
            "center": [
                144,
                149
            ],
            "matching": [
                98.0362376588303,
                28.216937249072295,
                14.829412033031891
            ],
            "original": [
                98.11491123212467,
                28.213453456009777,
                2.9167335268792884
            ],
            "radius": 120,
            "rotation_angle": -1.9636810249640386,
            "rotation_rad": -0.03427269934455944,
            "scale": 0.9630152529380602,
            "translation": [
                5.665579325442181,
                0.032645073926154566
            ]
        },
        "20220622": {
            "center": [
                152,
                144
            ],
            "matching": [
                98.52111602036469,
                28.195510381033934,
                5.614276500030875
            ],
            "original": [
                98.24329961648014,
                28.207774205361595,
                4.03011572753889
            ],
            "radius": 111,
            "rotation_angle": 0.21313562087309462,
            "rotation_rad": 0.0037199183375178527,
            "scale": 0.9646145081432743,
            "translation": [
                -0.9340489085836481,
                4.476960954279463
            ]
        },
        "20221014": {
            "center": [
                182,
                147
            ],
            "matching": [
                99.36604072658477,
                28.15842375313209,
                11.183135174150307
            ],
            "original": [
                97.63202904293804,
                28.234880457144932,
                3.6494274387617827
            ],
            "radius": 112,
            "rotation_angle": -2.355434445879199,
            "rotation_rad": -0.04111008639548021,
            "scale": 0.9960339338074078,
            "translation": [
                -43.73805686132689,
                4.481067417393952
            ]
        },
        "20230210": {
            "center": [
                170,
                163
            ],
            "matching": [
                101.02636389201349,
                28.0864563858295,
                4.66614930120387
            ],
            "original": [
                99.39231814773153,
                28.157275410075343,
                4.037198970564362
            ],
            "radius": 134,
            "rotation_angle": 43.16961496599547,
            "rotation_rad": 0.7534519179748409,
            "scale": 1.2246917327661362,
            "translation": [
                48.500152841016714,
                -10.339912848639763
            ]
        }
    },
    "10945774_L": {
        "20230322": {
            "center": [
                151,
                175
            ],
            "matching": [
                99.1137359497047,
                28.16946514316314,
                6.323579896707707
            ],
            "original": [
                102.49661522829746,
                28.02370837056084,
                5.097718636514631
            ],
            "radius": 125,
            "rotation_angle": 6.438949344909279,
            "rotation_rad": 0.1123808664377989,
            "scale": 1.604205747574209,
            "translation": [
                -91.69776140227951,
                -21.724004283310435
            ]
        }
    },
    "11092644_R": {
        "20220621": {
            "center": [
                176,
                169
            ],
            "matching": [
                100.26821485164746,
                28.1191707791993,
                6.233402279277744
            ],
            "original": [
                99.57302879624065,
                28.14938643239611,
                4.345323110744604
            ],
            "radius": 119,
            "rotation_angle": -4.355490694026491,
            "rotation_rad": -0.07601765315073519,
            "scale": 1.1268807939947922,
            "translation": [
                -7.3187621362827,
                9.982805421606443
            ]
        },
        "20230314": {
            "center": [
                142,
                142
            ],
            "radius": 80,
            "rotation_angle": 0,
            "rotation_rad": 0,
            "scale": 1,
            "translation": [
                0,
                0
            ]
        }
    },
    "11613611_R": {
        "20220310": {
            "center": [
                205,
                171
            ],
            "radius": 99,
            "rotation_angle": 0,
            "rotation_rad": 0,
            "scale": 1,
            "translation": [
                0,
                0
            ]
        }
    },
    "11663153_L": {
        "20230508": {
            "center": [
                154,
                151
            ],
            "radius": 96,
            "rotation_angle": 0,
            "rotation_rad": 0,
            "scale": 1,
            "translation": [
                0,
                0
            ]
        }
    },
    "11673305_L": {
        "20211202": {
            "center": [
                122,
                123
            ],
            "radius": 120,
            "rotation_angle": 0,
            "rotation_rad": 0,
            "scale": 1,
            "translation": [
                0,
                0
            ]
        },
        "20220519": {
            "center": [
                107,
                113
            ],
            "radius": 107,
            "rotation_angle": 0,
            "rotation_rad": 0,
            "scale": 1,
            "translation": [
                0,
                0
            ]
        }
    },
    "11990421_L": {
        "20210713": {
            "center": [
                113,
                145
            ],
            "radius": 99,
            "rotation_angle": 0,
            "rotation_rad": 0,
            "scale": 1,
            "translation": [
                0,
                0
            ]
        },
        "20220106": {
            "center": [
                114,
                135
            ],
            "radius": 87,
            "rotation_angle": 0,
            "rotation_rad": 0,
            "scale": 1,
            "translation": [
                0,
                0
            ]
        },
        "20220412": {
            "center": [
                143,
                144
            ],
            "radius": 102,
            "rotation_angle": 0,
            "rotation_rad": 0,
            "scale": 1,
            "translation": [
                0,
                0
            ]
        }
    },
    "11990421_R": {
        "20210713": {
            "center": [
                137,
                190
            ],
            "matching": [
                97.0481466489331,
                28.26093114887238,
                12.412789599684627
            ],
            "original": [
                97.73534956340715,
                28.2302869025392,
                5.926859606703137
            ],
            "radius": 110,
            "rotation_angle": 0.6267881998095801,
            "rotation_rad": 0.010939517799325268,
            "scale": 1.0030187491861877,
            "translation": [
                1.2965452990158823,
                -19.687545476387974
            ]
        },
        "20220106": {
            "center": [
                172,
                213
            ],
            "radius": 91,
            "rotation_angle": 0,
            "rotation_rad": 0,
            "scale": 1,
            "translation": [
                0,
                0
            ]
        },
        "20220412": {
            "center": [
                134,
                188
            ],
            "matching": [
                96.63326483202287,
                28.27953708094787,
                8.110761106541016
            ],
            "original": [
                99.06587294496069,
                28.1715629007849,
                6.507336929690541
            ],
            "radius": 96,
            "rotation_angle": 6.541283259404382,
            "rotation_rad": 0.1141669301821928,
            "scale": 0.997968430035811,
            "translation": [
                9.6258626109219,
                -23.755546546336248
            ]
        }
    },
    "12291088_L": {
        "20211224": {
            "center": [
                154,
                149
            ],
            "matching": [
                100.54054359368293,
                28.107391318646677,
                20.575327871108705
            ],
            "original": [
                102.59411219809765,
                28.019579232231916,
                0.10423344025337387
            ],
            "radius": 104,
            "rotation_angle": 0.42986702862900994,
            "rotation_rad": 0.00750259499534095,
            "scale": 0.9973707465844085,
            "translation": [
                5.647977206959496,
                3.3608999535273725
            ]
        },
        "20220429": {
            "center": [
                158,
                151
            ],
            "matching": [
                101.98221025794413,
                28.04555940680791,
                4.646643946649901
            ],
            "original": [
                100.4149183153157,
                28.1128212155772,
                16.200448098949447
            ],
            "radius": 103,
            "rotation_angle": -11.129315113656231,
            "rotation_rad": -0.19424319222526817,
            "scale": 0.6553608840737225,
            "translation": [
                13.864776552700846,
                66.95256823333392
            ]
        },
        "20220715": {
            "center": [
                154,
                143
            ],
            "matching": [
                99.47028068244359,
                28.153870174444865,
                25.84695491419139
            ],
            "original": [
                102.73166620803522,
                28.01376028861165,
                3.665996721067329
            ],
            "radius": 120,
            "rotation_angle": -1.0371487575694742,
            "rotation_rad": -0.018101660652555786,
            "scale": 1.0058333917397673,
            "translation": [
                0.5510306805870329,
                13.513216748336525
            ]
        },
        "20221028": {
            "center": [
                140,
                146
            ],
            "matching": [
                101.45131750398147,
                28.06822669469037,
                9.757416384472783
            ],
            "original": [
                101.84437285845277,
                28.05143322662169,
                3.123749602945592
            ],
            "radius": 107,
            "rotation_angle": 3.268797195694954,
            "rotation_rad": 0.057051273644834366,
            "scale": 1.037807825673958,
            "translation": [
                21.056966301022506,
                5.150560251758783
            ]
        },
        "20230224": {
            "center": [
                146,
                149
            ],
            "matching": [
                99.46141645966716,
                28.154257210105445,
                24.75885907967857
            ],
            "original": [
                101.68980396272843,
                28.05802950764341,
                3.4686807168186915
            ],
            "radius": 117,
            "rotation_angle": -2.004514968443171,
            "rotation_rad": -0.034985386104843565,
            "scale": 0.9616269378420806,
            "translation": [
                13.763296240338782,
                8.989152046895313
            ]
        },
        "20230519": {
            "center": [
                156,
                152
            ],
            "matching": [
                100.90809422031252,
                28.091543568289534,
                14.719887343505356
            ],
            "original": [
                101.45187654348332,
                28.068202763300626,
                5.344696661948415
            ],
            "radius": 117,
            "rotation_angle": -1.5883362702000643,
            "rotation_rad": -0.027721697543837416,
            "scale": 0.9799087185706805,
            "translation": [
                -0.8030398847227573,
                2.1076328626763257
            ]
        }
    },
    "12586387_L": {
        "20220518": {
            "center": [
                158,
                151
            ],
            "matching": [
                98.6312487792548,
                28.19065829067361,
                10.72160632800467
            ],
            "original": [
                97.90593655571769,
                28.222713346906893,
                6.568502508489135
            ],
            "radius": 104,
            "rotation_angle": 4.03148323807303,
            "rotation_rad": 0.07036265624333679,
            "scale": 1.04551387596751,
            "translation": [
                0.5358895660840943,
                -4.520109474286109
            ]
        },
        "20220629": {
            "center": [
                122,
                159
            ],
            "matching": [
                100.68328136665056,
                28.101229996788433,
                6.037466836004639
            ],
            "original": [
                96.42953756971586,
                28.28870276771645,
                5.965942809662131
            ],
            "radius": 122,
            "rotation_angle": -30.5437496090715,
            "rotation_rad": -0.5330889965830286,
            "scale": 0.7110925901378435,
            "translation": [
                25.25368377036463,
                65.59335545884001
            ]
        },
        "20221017": {
            "center": [
                184,
                191
            ],
            "matching": [
                100.18863507950601,
                28.122619008355816,
                5.900557783879499
            ],
            "original": [
                104.42688406382005,
                27.942680413440698,
                4.832312488600932
            ],
            "radius": 112,
            "rotation_angle": 12.28236589336352,
            "rotation_rad": 0.2143677247738482,
            "scale": 1.8353831040862252,
            "translation": [
                -13.102207507194606,
                -35.81262888156028
            ]
        },
        "20230116": {
            "center": [
                167,
                138
            ],
            "radius": 98,
            "rotation_angle": 0,
            "rotation_rad": 0,
            "scale": 1,
            "translation": [
                0,
                0
            ]
        }
    },
    "12586387_R": {
        "20220518": {
            "center": [
                137,
                138
            ],
            "matching": [
                97.16300842608968,
                28.255794076102525,
                11.084305964102741
            ],
            "original": [
                97.18569760856248,
                28.25478004446911,
                5.627473119838893
            ],
            "radius": 130,
            "rotation_angle": 2.0401622237140136,
            "rotation_rad": 0.03560754807861867,
            "scale": 0.9451012910024387,
            "translation": [
                24.049623517415974,
                4.566759841765746
            ]
        },
        "20220629": {
            "center": [
                155,
                146
            ],
            "radius": 122,
            "rotation_angle": 0,
            "rotation_rad": 0,
            "scale": 1,
            "translation": [
                0,
                0
            ]
        },
        "20221017": {
            "center": [
                64,
                179
            ],
            "radius": 64,
            "rotation_angle": 0,
            "rotation_rad": 0,
            "scale": 1,
            "translation": [
                0,
                0
            ]
        },
        "20230116": {
            "center": [
                158,
                132
            ],
            "matching": [
                97.74053125715594,
                28.230056656127918,
                10.795557678207043
            ],
            "original": [
                103.06410579345088,
                27.999729212881515,
                5.7690476179424985
            ],
            "radius": 125,
            "rotation_angle": -2.0488575761709047,
            "rotation_rad": -0.0357593106086128,
            "scale": 1.0451523184618605,
            "translation": [
                -5.441408103799468,
                16.38680647821028
            ]
        }
    },
    "12656149_R": {
        "20220801": {
            "center": [
                141,
                144
            ],
            "radius": 98,
            "rotation_angle": 0,
            "rotation_rad": 0,
            "scale": 1,
            "translation": [
                0,
                0
            ]
        },
        "20220919": {
            "center": [
                141,
                144
            ],
            "radius": 99,
            "rotation_angle": 0,
            "rotation_rad": 0,
            "scale": 1,
            "translation": [
                0,
                0
            ]
        }
    },
    "12814323_L": {
        "20210809": {
            "center": [
                150,
                127
            ],
            "radius": 113,
            "rotation_angle": 0,
            "rotation_rad": 0,
            "scale": 1,
            "translation": [
                0,
                0
            ]
        },
        "20220328": {
            "center": [
                162,
                151
            ],
            "radius": 101,
            "rotation_angle": 0,
            "rotation_rad": 0,
            "scale": 1,
            "translation": [
                0,
                0
            ]
        }
    },
    "13319575_L": {
        "20220215": {
            "center": [
                152,
                143
            ],
            "radius": 102,
            "rotation_angle": -2.6607032768634027,
            "rotation_rad": -0.04643803259986864,
            "scale": 0.7734213216551354,
            "translation": [
                10.8089627230571,
                32.48422037367608
            ]
        }
    },
    "13319575_R": {
        "20220215": {
            "center": [
                169,
                185
            ],
            "radius": 105,
            "rotation_angle": 0,
            "rotation_rad": 0,
            "scale": 1,
            "translation": [
                0,
                0
            ]
        }
    },
    "13382321_L": {
        "20230419": {
            "center": [
                151,
                156
            ],
            "radius": 130,
            "rotation_angle": 0,
            "rotation_rad": 0,
            "scale": 1,
            "translation": [
                0,
                0
            ]
        }
    },
    "13820694_R": {
        "20211129": {
            "center": [
                129,
                142
            ],
            "matching": [
                100.62876761592233,
                28.103582068790832,
                5.4005036985851325
            ],
            "original": [
                100.62876761592233,
                28.103582068790832,
                5.4005036985851325
            ],
            "radius": 129,
            "rotation_angle": 0,
            "rotation_rad": 0,
            "scale": 1,
            "translation": [
                0,
                0
            ]
        },
        "20220429": {
            "center": [
                145,
                146
            ],
            "radius": 145,
            "rotation_angle": 0,
            "rotation_rad": 0,
            "scale": 1,
            "translation": [
                0,
                0
            ]
        },
        "20220729": {
            "center": [
                135,
                145
            ],
            "radius": 123,
            "rotation_angle": 0,
            "rotation_rad": 0,
            "scale": 1,
            "translation": [
                0,
                0
            ]
        },
        "20221125": {
            "center": [
                142,
                143
            ],
            "radius": 101,
            "rotation_angle": 0,
            "rotation_rad": 0,
            "scale": 1,
            "translation": [
                0,
                0
            ]
        },
        "20230324": {
            "center": [
                141,
                155
            ],
            "radius": 116,
            "rotation_angle": 0,
            "rotation_rad": 0,
            "scale": 1,
            "translation": [
                0,
                0
            ]
        }
    },
    "14112463_R": {
        "20201022": {
            "center": [
                153,
                151
            ],
            "matching": [
                100.73545536927956,
                28.098980068870652,
                6.607046547206645
            ],
            "original": [
                101.43025600362483,
                28.06912839248975,
                4.974202997822803
            ],
            "radius": 119,
            "rotation_angle": 0.08540276554192669,
            "rotation_rad": 0.00149055944901538,
            "scale": 1.0019293076836087,
            "translation": [
                10.60998216061575,
                -14.855747142650095
            ]
        },
        "20210408": {
            "center": [
                181,
                170
            ],
            "matching": [
                104.36636304779765,
                27.94519811402704,
                4.241613511671737
            ],
            "original": [
                104.36636304779765,
                27.94519811402704,
                4.241613511671737
            ],
            "radius": 105,
            "rotation_angle": 0,
            "rotation_rad": 0,
            "scale": 1,
            "translation": [
                0,
                0
            ]
        },
        "20210624": {
            "center": [
                141,
                186
            ],
            "radius": 110,
            "rotation_angle": 0,
            "rotation_rad": 0,
            "scale": 1,
            "translation": [
                0,
                0
            ]
        },
        "20220209": {
            "center": [
                161,
                181
            ],
            "radius": 123,
            "rotation_angle": 0,
            "rotation_rad": 0,
            "scale": 1,
            "translation": [
                0,
                0
            ]
        }
    },
    "14306165_L": {
        "20211227": {
            "center": [
                151,
                179
            ],
            "matching": [
                98.45237389603462,
                28.198541685042976,
                6.605659921023686
            ],
            "original": [
                97.21009424456167,
                28.25368996691691,
                7.104431845225423
            ],
            "radius": 84,
            "rotation_angle": 26.31430966715109,
            "rotation_rad": 0.45927134408115966,
            "scale": 1.4341674140622824,
            "translation": [
                3.9048520532228963,
                -19.631790467355827
            ]
        }
    },
    "16095800_R": {
        "20210930": {
            "center": [
                151,
                146
            ],
            "matching": [
                97.29866983742457,
                28.24973457765183,
                36.05698434127102
            ],
            "original": [
                101.41452844236518,
                28.06980185255442,
                2.71517922232746
            ],
            "radius": 103,
            "rotation_angle": 0.19620315473600178,
            "rotation_rad": 0.0034243910529431366,
            "scale": 0.9903264336492104,
            "translation": [
                -4.329670042551953,
                0.7575613796235245
            ]
        }
    },
    "16341383_L": {
        "20220630": {
            "center": [
                155,
                194
            ],
            "radius": 110,
            "rotation_angle": 0,
            "rotation_rad": 0,
            "scale": 1,
            "translation": [
                0,
                0
            ]
        }
    },
    "17527028_R": {
        "20210617": {
            "center": [
                158,
                151
            ],
            "radius": 111,
            "rotation_angle": 0,
            "rotation_rad": 0,
            "scale": 1,
            "translation": [
                0,
                0
            ]
        }
    },
    "20256047_R": {
        "20210630": {
            "center": [
                152,
                154
            ],
            "radius": 116,
            "rotation_angle": -4.443785244322233,
            "rotation_rad": -0.07755868376496361,
            "scale": 0.9960262500556231,
            "translation": [
                8.326526024885297,
                11.004356564988555
            ]
        },
        "20210818": {
            "center": [
                154,
                159
            ],
            "radius": 104,
            "rotation_angle": -2.8229596281580474,
            "rotation_rad": -0.04926994016223275,
            "scale": 1.0068664460027703,
            "translation": [
                10.040662083626074,
                3.9774483960271567
            ]
        }
    },
    "20307089_L": {
        "20210720": {
            "center": [
                151,
                157
            ],
            "matching": [
                101.00908786797503,
                28.087199115074494,
                7.401228032702886
            ],
            "original": [
                100.992818911686,
                28.087898664704554,
                5.653252928000698
            ],
            "radius": 96,
            "rotation_angle": -3.555790218637533,
            "rotation_rad": -0.062060246825433985,
            "scale": 0.8852286946208325,
            "translation": [
                6.38873456990752,
                2.6472871933626934
            ]
        }
    },
    "20312202_L": {
        "20210809": {
            "center": [
                142,
                154
            ],
            "matching": [
                97.97811281762247,
                28.219512907280645,
                26.55755265202382
            ],
            "original": [
                100.94807665210652,
                28.089823120541688,
                3.4554408669342007
            ],
            "radius": 107,
            "rotation_angle": 1.7732215491739765,
            "rotation_rad": 0.030948554400400424,
            "scale": 1.01766746640672,
            "translation": [
                16.604784188078426,
                -8.350168957738703
            ]
        },
        "20220214": {
            "center": [
                153,
                152
            ],
            "matching": [
                99.72122342326246,
                28.142927628902395,
                12.409688757273415
            ],
            "original": [
                99.3062578166875,
                28.16103744299771,
                4.65844286337769
            ],
            "radius": 103,
            "rotation_angle": 0.7841146599351898,
            "rotation_rad": 0.013685382529024728,
            "scale": 0.9796379443279796,
            "translation": [
                7.244478889160391,
                -5.37872322435782
            ]
        }
    },
    "20342007_L": {
        "20211123": {
            "center": [
                149,
                130
            ],
            "radius": 112,
            "rotation_angle": 2.916597679525918,
            "rotation_rad": 0.05090423246375368,
            "scale": 1.02362430556319,
            "translation": [
                -1.3227465002028467,
                -3.049562012332883
            ]
        }
    },
    "20354860_R": {
        "20210920": {
            "center": [
                147,
                146
            ],
            "radius": 110,
            "rotation_angle": 0,
            "rotation_rad": 0,
            "scale": 1,
            "translation": [
                0,
                0
            ]
        },
        "20211108": {
            "center": [
                162,
                143
            ],
            "matching": [
                101.65593490182204,
                28.059476220663022,
                31.594769134958177
            ],
            "original": [
                105.05541305501504,
                27.916619262167778,
                2.4357547076620243
            ],
            "radius": 92,
            "rotation_angle": -0.5416097508231438,
            "rotation_rad": -0.009452873412769928,
            "scale": 1.0075498259423685,
            "translation": [
                -2.030221613863546,
                -4.941124629499889
            ]
        },
        "20211213": {
            "center": [
                163,
                152
            ],
            "radius": 102,
            "rotation_angle": 0,
            "rotation_rad": 0,
            "scale": 1,
            "translation": [
                0,
                0
            ]
        },
        "20220214": {
            "center": [
                166,
                138
            ],
            "matching": [
                102.15181086745848,
                28.038342909980845,
                13.135113425887962
            ],
            "original": [
                104.64799080480493,
                27.933494663753635,
                2.4664213431507838
            ],
            "radius": 107,
            "rotation_angle": 0.6988742723860104,
            "rotation_rad": 0.012197657110615568,
            "scale": 0.9739683384033228,
            "translation": [
                -4.975393784069354,
                1.6419831316273061
            ]
        }
    },
    "20402196_L": {
        "20210712": {
            "center": [
                138,
                174
            ],
            "radius": 130,
            "rotation_angle": 0,
            "rotation_rad": 0,
            "scale": 1,
            "translation": [
                0,
                0
            ]
        },
        "20211129": {
            "center": [
                146,
                161
            ],
            "radius": 93,
            "rotation_angle": 0,
            "rotation_rad": 0,
            "scale": 1,
            "translation": [
                0,
                0
            ]
        }
    },
    "20402196_R": {
        "20210712": {
            "center": [
                152,
                156
            ],
            "matching": [
                97.97702180739898,
                28.219561267301494,
                17.892711058480216
            ],
            "original": [
                94.9660798109223,
                28.355118501213386,
                23.224773918802196
            ],
            "radius": 99,
            "rotation_angle": -1.18782031083678,
            "rotation_rad": -0.02073137534616429,
            "scale": 0.9815247483128328,
            "translation": [
                1.8883229653367195,
                2.2870690549833697
            ]
        },
        "20211129": {
            "center": [
                157,
                166
            ],
            "matching": [
                99.02265307482178,
                28.173458028360926,
                8.944983111730288
            ],
            "original": [
                100.36522530925889,
                28.114970969867706,
                4.592725399492316
            ],
            "radius": 112,
            "rotation_angle": 1.2572267713454077,
            "rotation_rad": 0.021942746604195262,
            "scale": 0.9587618530959998,
            "translation": [
                0.4072242231960317,
                -13.829738214976778
            ]
        }
    },
    "20770192_L": {
        "20211224": {
            "center": [
                142,
                136
            ],
            "matching": [
                94.87757799809556,
                28.359167712251253,
                32.734836915625756
            ],
            "original": [
                98.9671763849213,
                28.1758918120552,
                4.163562182850263
            ],
            "radius": 136,
            "rotation_angle": -1.8615849100960362,
            "rotation_rad": -0.03249078598661846,
            "scale": 1.0194906485392028,
            "translation": [
                -13.560727108241117,
                2.9633398226311374
            ]
        },
        "20220107": {
            "center": [
                142,
                136
            ],
            "matching": [
                94.87529699197562,
                28.35927212472681,
                32.736511522335924
            ],
            "original": [
                98.9638902586632,
                28.176036018472622,
                4.160427699925533
            ],
            "radius": 136,
            "rotation_angle": -1.8615849100960362,
            "rotation_rad": -0.03249078598661846,
            "scale": 1.0194906485392028,
            "translation": [
                -13.560727108241117,
                2.9633398226311374
            ]
        }
    },
    "21091108_L": {
        "20220722": {
            "center": [
                164,
                146
            ],
            "radius": 91,
            "rotation_angle": 0,
            "rotation_rad": 0,
            "scale": 1,
            "translation": [
                0,
                0
            ]
        }
    },
    "21215427_L": {
        "20220505": {
            "center": [
                159,
                158
            ],
            "matching": [
                100.4647824850725,
                28.110665125725554,
                4.288381503176904
            ],
            "original": [
                101.32128518623827,
                28.073796710072795,
                5.289183846814141
            ],
            "radius": 112,
            "rotation_angle": 2.664742047011431,
            "rotation_rad": 0.04650852243668299,
            "scale": 1.0004882090292762,
            "translation": [
                -2.7495520500311983,
                -8.553276498612192
            ]
        }
    },
    "21215427_R": {
        "20220505": {
            "center": [
                155,
                151
            ],
            "radius": 149,
            "rotation_angle": 0,
            "rotation_rad": 0,
            "scale": 1,
            "translation": [
                0,
                0
            ]
        }
    },
    "21385315_L": {
        "20220621": {
            "center": [
                148,
                134
            ],
            "radius": 98,
            "rotation_angle": 0,
            "rotation_rad": 0,
            "scale": 1,
            "translation": [
                0,
                0
            ]
        }
    }
}